{
  "polled_at_utc": "2026-05-01T14:07:05Z",
  "polled_ts": 1777644425,
  "workflow_run_id": "25217355853",
  "trigger": "schedule",
  "config_dump": {"execution":{"force_notional_usd":44.0,"global_max_positions":20,"maker_only_entry":false},"git_sha":"0b6f99983c19","kills_and_filters":{"bad_entry_kill":{"age_sec":60,"enabled":true,"max_age_sec":90,"min_mfe_pct":0.05},"hour_veto":{"enabled":false,"hours":[4,6,7,9,14,15,16,19]},"liquidation_cascade":{"max_age_sec":180,"usd_threshold":150000.0,"window_sec":60},"wilson_auto_disable":{"enabled":true,"lookback_h":168.0,"n":50,"z":1.645}},"manual_disables":{"DISABLE_ENGINES_env":""},"now_utc":"2026-05-01T14:07:05.476300Z","pivot_engine":{"chase_gate_coins_n":20,"lookback":10,"rsi_overbought":70.0,"rsi_oversold":30.0,"wick_filter_on":true,"wick_ratio":1.2},"tp_sl_overrides_per_engine":{"sl_env_set":{"BB_REJ":false,"PIVOT":false},"sl_overrides_default_in_code":{"BB_REJ":"0.015","PIVOT":"0.015"},"tp_env_set":{"BB_REJ":false,"LIQ_CSCD":false,"PIVOT":false},"tp_overrides_default_in_code":{"BB_REJ":"0.003","LIQ_CSCD":"0.005","PIVOT":"0.003"}},"verified_engines":{"allowlist_default_in_code":"BB_REJ,LIQ_CSCD,PIVOT,CONFLUENCE_DAY+NEWS,CONFLUENCE_DAY+SNIPER","allowlist_effective":["BB_REJ","CONFLUENCE_DAY+NEWS","CONFLUENCE_DAY+SNIPER","LIQ_CSCD","PIVOT"],"env_var_set":false,"verified_engines_only":true},"verified_loser_baseline":{"enabled":true,"engines":["CONFLUENCE_BTC_WALL+DAY","CONFLUENCE_BTC_WALL+NEWS","CONFLUENCE_BTC_WALL+SNIPER","HL"]}}
,
  "diagnose": {"by_window":{"12h":{"best_engines":[["INV_CONFLUENCE_BTC_WALL+DAY",{"avg_loss":null,"avg_win":1.914,"b":16,"l":0,"n":17,"pnl":1.914,"w":1,"wr_pct":100.0}],["CONFLUENCE_OBI+SNIPER",{"avg_loss":-0.0017,"avg_win":0.4052,"b":0,"l":1,"n":3,"pnl":0.8088,"w":2,"wr_pct":66.7}],["CONFLUENCE_FUNDING+SNIPER",{"avg_loss":-0.2555,"avg_win":0.7125,"b":7,"l":1,"n":9,"pnl":0.457,"w":1,"wr_pct":50.0}],["INV_CONFLUENCE_BTC_WALL+SNIPER",{"avg_loss":-0.0003,"avg_win":0.4496,"b":15,"l":1,"n":17,"pnl":0.4493,"w":1,"wr_pct":50.0}],["CONFLUENCE_BTC_WALL+OBI+SNIPER",{"avg_loss":null,"avg_win":0.0018,"b":0,"l":0,"n":2,"pnl":0.0036,"w":2,"wr_pct":100.0}]],"n_closes":102,"noise":{"avg_loss":-0.0058,"avg_win":0.7879,"b":53,"l":4,"n":60,"pnl":2.3406,"w":3,"wr_pct":42.9},"real_total_pnl":1.0865,"system_A":{"avg_loss":null,"avg_win":null,"b":0,"l":0,"n":0,"pnl":0.0,"w":0,"wr_pct":null},"system_B":{"avg_loss":-0.0895,"avg_win":0.1804,"b":27,"l":6,"n":42,"pnl":1.0865,"w":9,"wr_pct":60.0},"worst_engines":[["CONFLUENCE_BTC_WALL+OBI",{"avg_loss":-0.2227,"avg_win":0.032,"b":4,"l":1,"n":8,"pnl":-0.1266,"w":3,"wr_pct":75.0}],["CONFLUENCE_FUNDING+NEWS",{"avg_loss":-0.0466,"avg_win":null,"b":3,"l":1,"n":4,"pnl":-0.0466,"w":0,"wr_pct":0.0}],["INV_CONFLUENCE_BTC_WALL+DAY+SNIPER",{"avg_loss":-0.0076,"avg_win":null,"b":16,"l":3,"n":19,"pnl":-0.0227,"w":0,"wr_pct":0.0}],["CONFLUENCE_BTC_WALL+CVD+DAY",{"avg_loss":-0.0053,"avg_win":null,"b":0,"l":1,"n":1,"pnl":-0.0053,"w":0,"wr_pct":0.0}],["CONFLUENCE_DAY+FUNDING+SNIPER",{"avg_loss":-0.0052,"avg_win":null,"b":0,"l":1,"n":1,"pnl":-0.0052,"w":0,"wr_pct":0.0}]]},"168h":{"best_engines":[["CONFLUENCE_SNIPER",{"avg_loss":-0.0108,"avg_win":124.8101,"b":11,"l":18,"n":37,"pnl":998.2867,"w":8,"wr_pct":30.8}],["untagged_legacy",{"avg_loss":-0.1777,"avg_win":0.2466,"b":74,"l":26,"n":130,"pnl":2.7793,"w":30,"wr_pct":53.6}],["INV_CONFLUENCE_BTC_WALL+DAY",{"avg_loss":-0.0002,"avg_win":1.914,"b":17,"l":1,"n":19,"pnl":1.9138,"w":1,"wr_pct":50.0}],["CONFLUENCE_DAY+NEWS",{"avg_loss":-0.0019,"avg_win":0.381,"b":8,"l":7,"n":19,"pnl":1.5105,"w":4,"wr_pct":36.4}],["CONFLUENCE_OBI+SNIPER",{"avg_loss":-0.0017,"avg_win":0.4052,"b":1,"l":1,"n":4,"pnl":0.8088,"w":2,"wr_pct":66.7}]],"n_closes":899,"noise":{"avg_loss":-0.1958,"avg_win":0.1714,"b":169,"l":68,"n":320,"pnl":0.9077,"w":83,"wr_pct":55.0},"real_total_pnl":988.4132,"system_A":{"avg_loss":-0.6561,"avg_win":0.0828,"b":24,"l":12,"n":64,"pnl":-5.5557,"w":28,"wr_pct":70.0},"system_B":{"avg_loss":-0.0549,"avg_win":6.442,"b":159,"l":200,"n":515,"pnl":993.9689,"w":156,"wr_pct":43.8},"worst_engines":[["RECONCILED",{"avg_loss":-0.2432,"avg_win":0.091,"b":41,"l":35,"n":125,"pnl":-4.051,"w":49,"wr_pct":58.3}],["TREND_CONT",{"avg_loss":-0.6842,"avg_win":0.0464,"b":4,"l":3,"n":9,"pnl":-1.9599,"w":2,"wr_pct":40.0}],["FUNDING_MR",{"avg_loss":-0.5776,"avg_win":0.0518,"b":7,"l":4,"n":20,"pnl":-1.8442,"w":9,"wr_pct":69.2}],["CONFLUENCE_BTC_WALL+NEWS",{"avg_loss":-0.0684,"avg_win":0.0169,"b":14,"l":30,"n":64,"pnl":-1.7153,"w":20,"wr_pct":40.0}],["CONFLUENCE_BTC_WALL",{"avg_loss":-0.192,"avg_win":0.0144,"b":1,"l":8,"n":12,"pnl":-1.4926,"w":3,"wr_pct":27.3}]]},"1h":{"best_engines":[],"n_closes":0,"noise":{"avg_loss":null,"avg_win":null,"b":0,"l":0,"n":0,"pnl":0.0,"w":0,"wr_pct":null},"real_total_pnl":0.0,"system_A":{"avg_loss":null,"avg_win":null,"b":0,"l":0,"n":0,"pnl":0.0,"w":0,"wr_pct":null},"system_B":{"avg_loss":null,"avg_win":null,"b":0,"l":0,"n":0,"pnl":0.0,"w":0,"wr_pct":null},"worst_engines":[]},"24h":{"best_engines":[["INV_CONFLUENCE_BTC_WALL+DAY",{"avg_loss":-0.0002,"avg_win":1.914,"b":17,"l":1,"n":19,"pnl":1.9138,"w":1,"wr_pct":50.0}],["CONFLUENCE_OBI+SNIPER",{"avg_loss":-0.0017,"avg_win":0.4052,"b":0,"l":1,"n":3,"pnl":0.8088,"w":2,"wr_pct":66.7}],["CONFLUENCE_FUNDING+SNIPER",{"avg_loss":-0.2555,"avg_win":0.7125,"b":7,"l":1,"n":9,"pnl":0.457,"w":1,"wr_pct":50.0}],["INV_CONFLUENCE_BTC_WALL+SNIPER",{"avg_loss":-0.0539,"avg_win":0.225,"b":15,"l":3,"n":20,"pnl":0.2883,"w":2,"wr_pct":40.0}],["CONFLUENCE_BTC_WALL+CVD",{"avg_loss":null,"avg_win":0.0198,"b":1,"l":0,"n":3,"pnl":0.0396,"w":2,"wr_pct":100.0}]],"n_closes":133,"noise":{"avg_loss":-0.0264,"avg_win":0.591,"b":54,"l":7,"n":65,"pnl":2.1794,"w":4,"wr_pct":36.4},"real_total_pnl":1.1459,"system_A":{"avg_loss":null,"avg_win":null,"b":0,"l":0,"n":0,"pnl":0.0,"w":0,"wr_pct":null},"system_B":{"avg_loss":-0.0378,"avg_win":0.1036,"b":31,"l":19,"n":68,"pnl":1.1459,"w":18,"wr_pct":48.6},"worst_engines":[["CONFLUENCE_DAY+OBI",{"avg_loss":-0.0783,"avg_win":null,"b":0,"l":1,"n":1,"pnl":-0.0783,"w":0,"wr_pct":0.0}],["CONFLUENCE_FUNDING+NEWS",{"avg_loss":-0.0466,"avg_win":null,"b":3,"l":1,"n":4,"pnl":-0.0466,"w":0,"wr_pct":0.0}],["CONFLUENCE_BTC_WALL+OBI",{"avg_loss":-0.0498,"avg_win":0.0387,"b":5,"l":6,"n":18,"pnl":-0.0282,"w":7,"wr_pct":53.8}],["INV_CONFLUENCE_BTC_WALL+DAY+SNIPER",{"avg_loss":-0.0076,"avg_win":null,"b":16,"l":3,"n":19,"pnl":-0.0227,"w":0,"wr_pct":0.0}],["CONFLUENCE_DAY+OI+SNIPER",{"avg_loss":-0.0053,"avg_win":null,"b":0,"l":1,"n":1,"pnl":-0.0053,"w":0,"wr_pct":0.0}]]},"336h":{"best_engines":[["CONFLUENCE_SNIPER",{"avg_loss":-0.0108,"avg_win":124.8101,"b":11,"l":18,"n":37,"pnl":998.2867,"w":8,"wr_pct":30.8}],["untagged_legacy",{"avg_loss":-0.1777,"avg_win":0.2466,"b":123,"l":26,"n":179,"pnl":2.7793,"w":30,"wr_pct":53.6}],["INV_CONFLUENCE_BTC_WALL+DAY",{"avg_loss":-0.0002,"avg_win":1.914,"b":17,"l":1,"n":19,"pnl":1.9138,"w":1,"wr_pct":50.0}],["CONFLUENCE_DAY+NEWS",{"avg_loss":-0.0019,"avg_win":0.381,"b":8,"l":7,"n":19,"pnl":1.5105,"w":4,"wr_pct":36.4}],["CONFLUENCE_OBI+SNIPER",{"avg_loss":-0.0017,"avg_win":0.4052,"b":1,"l":1,"n":4,"pnl":0.8088,"w":2,"wr_pct":66.7}]],"n_closes":975,"noise":{"avg_loss":-0.3328,"avg_win":0.2263,"b":219,"l":87,"n":396,"pnl":-8.5829,"w":90,"wr_pct":50.8},"real_total_pnl":988.4132,"system_A":{"avg_loss":-0.6561,"avg_win":0.0828,"b":24,"l":12,"n":64,"pnl":-5.5557,"w":28,"wr_pct":70.0},"system_B":{"avg_loss":-0.0549,"avg_win":6.442,"b":159,"l":200,"n":515,"pnl":993.9689,"w":156,"wr_pct":43.8},"worst_engines":[["HL",{"avg_loss":-0.8228,"avg_win":0.8776,"b":1,"l":19,"n":27,"pnl":-9.4906,"w":7,"wr_pct":26.9}],["RECONCILED",{"avg_loss":-0.2432,"avg_win":0.091,"b":41,"l":35,"n":125,"pnl":-4.051,"w":49,"wr_pct":58.3}],["TREND_CONT",{"avg_loss":-0.6842,"avg_win":0.0464,"b":4,"l":3,"n":9,"pnl":-1.9599,"w":2,"wr_pct":40.0}],["FUNDING_MR",{"avg_loss":-0.5776,"avg_win":0.0518,"b":7,"l":4,"n":20,"pnl":-1.8442,"w":9,"wr_pct":69.2}],["CONFLUENCE_BTC_WALL+NEWS",{"avg_loss":-0.0684,"avg_win":0.0169,"b":14,"l":30,"n":64,"pnl":-1.7153,"w":20,"wr_pct":40.0}]]},"48h":{"best_engines":[["untagged_legacy",{"avg_loss":-0.1562,"avg_win":0.7442,"b":12,"l":7,"n":24,"pnl":2.6277,"w":5,"wr_pct":41.7}],["INV_CONFLUENCE_BTC_WALL+DAY",{"avg_loss":-0.0002,"avg_win":1.914,"b":17,"l":1,"n":19,"pnl":1.9138,"w":1,"wr_pct":50.0}],["CONFLUENCE_OBI+SNIPER",{"avg_loss":-0.0017,"avg_win":0.4052,"b":0,"l":1,"n":3,"pnl":0.8088,"w":2,"wr_pct":66.7}],["CONFLUENCE_FUNDING+SNIPER",{"avg_loss":-0.2555,"avg_win":0.7125,"b":7,"l":1,"n":9,"pnl":0.457,"w":1,"wr_pct":50.0}],["CONFLUENCE_OBI",{"avg_loss":null,"avg_win":0.0748,"b":2,"l":0,"n":8,"pnl":0.4491,"w":6,"wr_pct":100.0}]],"n_closes":249,"noise":{"avg_loss":-0.0913,"avg_win":0.6761,"b":66,"l":14,"n":89,"pnl":4.8071,"w":9,"wr_pct":39.1},"real_total_pnl":-2.2476,"system_A":{"avg_loss":null,"avg_win":null,"b":0,"l":0,"n":0,"pnl":0.0,"w":0,"wr_pct":null},"system_B":{"avg_loss":-0.1004,"avg_win":0.0652,"b":65,"l":51,"n":160,"pnl":-2.2476,"w":44,"wr_pct":46.3},"worst_engines":[["CONFLUENCE_BTC_WALL",{"avg_loss":-0.192,"avg_win":0.0144,"b":1,"l":8,"n":12,"pnl":-1.4926,"w":3,"wr_pct":27.3}],["CONFLUENCE_BTC_WALL+OBI",{"avg_loss":-0.1307,"avg_win":0.0387,"b":12,"l":10,"n":29,"pnl":-1.0359,"w":7,"wr_pct":41.2}],["CONFLUENCE_NEWS+SNIPER",{"avg_loss":-0.1646,"avg_win":null,"b":0,"l":3,"n":3,"pnl":-0.4938,"w":0,"wr_pct":0.0}],["CONFLUENCE_BTC_WALL+CVD",{"avg_loss":-0.5191,"avg_win":0.0233,"b":1,"l":1,"n":5,"pnl":-0.4493,"w":3,"wr_pct":75.0}],["CONFLUENCE_FUNDING",{"avg_loss":-0.1646,"avg_win":0.0007,"b":2,"l":2,"n":7,"pnl":-0.327,"w":3,"wr_pct":60.0}]]},"6h":{"best_engines":[["INV_CONFLUENCE_BTC_WALL+DAY",{"avg_loss":null,"avg_win":1.914,"b":16,"l":0,"n":17,"pnl":1.914,"w":1,"wr_pct":100.0}],["CONFLUENCE_FUNDING+SNIPER",{"avg_loss":-0.2555,"avg_win":0.7125,"b":7,"l":1,"n":9,"pnl":0.457,"w":1,"wr_pct":50.0}],["CONFLUENCE_DAY+NEWS",{"avg_loss":null,"avg_win":null,"b":3,"l":0,"n":3,"pnl":0.0,"w":0,"wr_pct":null}],["CONFLUENCE_FUNDING+NEWS+SNIPER",{"avg_loss":null,"avg_win":null,"b":3,"l":0,"n":3,"pnl":0.0,"w":0,"wr_pct":null}],["INV_CONFLUENCE_NEWS+SNIPER",{"avg_loss":null,"avg_win":null,"b":6,"l":0,"n":6,"pnl":0.0,"w":0,"wr_pct":null}]],"n_closes":85,"noise":{"avg_loss":-0.0087,"avg_win":1.914,"b":52,"l":2,"n":55,"pnl":1.8966,"w":1,"wr_pct":33.3},"real_total_pnl":0.4052,"system_A":{"avg_loss":null,"avg_win":null,"b":0,"l":0,"n":0,"pnl":0.0,"w":0,"wr_pct":null},"system_B":{"avg_loss":-0.1024,"avg_win":0.7125,"b":26,"l":3,"n":30,"pnl":0.4052,"w":1,"wr_pct":25.0},"worst_engines":[["CONFLUENCE_FUNDING+NEWS",{"avg_loss":-0.0466,"avg_win":null,"b":3,"l":1,"n":4,"pnl":-0.0466,"w":0,"wr_pct":0.0}],["INV_CONFLUENCE_BTC_WALL+DAY+SNIPER",{"avg_loss":-0.0087,"avg_win":null,"b":15,"l":2,"n":17,"pnl":-0.0174,"w":0,"wr_pct":0.0}],["CONFLUENCE_DAY+FUNDING+SNIPER",{"avg_loss":-0.0052,"avg_win":null,"b":0,"l":1,"n":1,"pnl":-0.0052,"w":0,"wr_pct":0.0}],["INV_CONFLUENCE_BTC_WALL+SNIPER",{"avg_loss":null,"avg_win":null,"b":15,"l":0,"n":15,"pnl":0.0,"w":0,"wr_pct":null}],["CONFLUENCE_BTC_WALL+OBI",{"avg_loss":null,"avg_win":null,"b":4,"l":0,"n":4,"pnl":0.0,"w":0,"wr_pct":null}]]},"72h":{"best_engines":[["untagged_legacy",{"avg_loss":-0.287,"avg_win":0.4817,"b":24,"l":13,"n":51,"pnl":3.0122,"w":14,"wr_pct":51.9}],["INV_CONFLUENCE_BTC_WALL+DAY",{"avg_loss":-0.0002,"avg_win":1.914,"b":17,"l":1,"n":19,"pnl":1.9138,"w":1,"wr_pct":50.0}],["CONFLUENCE_OBI+SNIPER",{"avg_loss":-0.0017,"avg_win":0.4052,"b":0,"l":1,"n":3,"pnl":0.8088,"w":2,"wr_pct":66.7}],["CONFLUENCE_FUNDING+SNIPER",{"avg_loss":-0.2555,"avg_win":0.7125,"b":7,"l":1,"n":9,"pnl":0.457,"w":1,"wr_pct":50.0}],["CONFLUENCE_OBI",{"avg_loss":null,"avg_win":0.0748,"b":2,"l":0,"n":8,"pnl":0.4491,"w":6,"wr_pct":100.0}]],"n_closes":310,"noise":{"avg_loss":-0.1958,"avg_win":0.506,"b":78,"l":20,"n":116,"pnl":5.1916,"w":18,"wr_pct":47.4},"real_total_pnl":-4.9565,"system_A":{"avg_loss":null,"avg_win":null,"b":0,"l":0,"n":0,"pnl":0.0,"w":0,"wr_pct":null},"system_B":{"avg_loss":-0.1074,"avg_win":0.0554,"b":69,"l":73,"n":194,"pnl":-4.9565,"w":52,"wr_pct":41.6},"worst_engines":[["CONFLUENCE_BTC_WALL+NEWS",{"avg_loss":-0.2219,"avg_win":null,"b":2,"l":9,"n":11,"pnl":-1.9968,"w":0,"wr_pct":0.0}],["CONFLUENCE_BTC_WALL",{"avg_loss":-0.192,"avg_win":0.0144,"b":1,"l":8,"n":12,"pnl":-1.4926,"w":3,"wr_pct":27.3}],["CONFLUENCE_BTC_WALL+OBI",{"avg_loss":-0.1091,"avg_win":0.0387,"b":12,"l":12,"n":31,"pnl":-1.0389,"w":7,"wr_pct":36.8}],["CONFLUENCE_BTC_WALL+DAY+NEWS",{"avg_loss":-0.2265,"avg_win":0.0015,"b":0,"l":3,"n":7,"pnl":-0.6733,"w":4,"wr_pct":57.1}],["CONFLUENCE_NEWS+SNIPER",{"avg_loss":-0.1646,"avg_win":null,"b":0,"l":3,"n":3,"pnl":-0.4938,"w":0,"wr_pct":0.0}]]}},"deploy_correlation":[{"flip_iso":"2026-04-27T13:00:00+00:00","gap_minutes":null,"nearest_deploy":null,"system":"system_A"},{"flip_iso":"2026-05-01T09:00:00+00:00","gap_minutes":null,"nearest_deploy":null,"system":"system_B"}],"err":null,"hourly_series":[{"closes":1,"cum_A":0.0,"cum_B":0.0,"hour_utc":"2026-04-24T15:00:00+00:00","pnl_A":0.0,"pnl_B":0.0},{"closes":1,"cum_A":0.0,"cum_B":0.0,"hour_utc":"2026-04-24T16:00:00+00:00","pnl_A":0.0,"pnl_B":0.0},{"closes":1,"cum_A":0.0,"cum_B":0.0,"hour_utc":"2026-04-24T18:00:00+00:00","pnl_A":0.0,"pnl_B":0.0},{"closes":1,"cum_A":0.0,"cum_B":0.0,"hour_utc":"2026-04-24T19:00:00+00:00","pnl_A":0.0,"pnl_B":0.0},{"closes":3,"cum_A":0.0,"cum_B":0.0,"hour_utc":"2026-04-24T20:00:00+00:00","pnl_A":0.0,"pnl_B":0.0},{"closes":1,"cum_A":0.0,"cum_B":0.0,"hour_utc":"2026-04-24T21:00:00+00:00","pnl_A":0.0,"pnl_B":0.0},{"closes":4,"cum_A":0.0,"cum_B":0.0,"hour_utc":"2026-04-25T00:00:00+00:00","pnl_A":0.0,"pnl_B":0.0},{"closes":1,"cum_A":0.0,"cum_B":0.0,"hour_utc":"2026-04-25T01:00:00+00:00","pnl_A":0.0,"pnl_B":0.0},{"closes":6,"cum_A":0.0,"cum_B":0.0,"hour_utc":"2026-04-25T05:00:00+00:00","pnl_A":0.0,"pnl_B":0.0},{"closes":3,"cum_A":0.0,"cum_B":0.0,"hour_utc":"2026-04-25T06:00:00+00:00","pnl_A":0.0,"pnl_B":0.0},{"closes":2,"cum_A":0.0,"cum_B":0.0,"hour_utc":"2026-04-25T07:00:00+00:00","pnl_A":0.0,"pnl_B":0.0},{"closes":4,"cum_A":0.0,"cum_B":0.0,"hour_utc":"2026-04-25T09:00:00+00:00","pnl_A":0.0,"pnl_B":0.0},{"closes":2,"cum_A":0.0,"cum_B":0.0,"hour_utc":"2026-04-25T10:00:00+00:00","pnl_A":0.0,"pnl_B":0.0},{"closes":12,"cum_A":0.0,"cum_B":0.0,"hour_utc":"2026-04-25T11:00:00+00:00","pnl_A":0.0,"pnl_B":0.0},{"closes":6,"cum_A":0.0,"cum_B":0.0,"hour_utc":"2026-04-25T12:00:00+00:00","pnl_A":0.0,"pnl_B":0.0},{"closes":1,"cum_A":0.0,"cum_B":0.0,"hour_utc":"2026-04-25T13:00:00+00:00","pnl_A":0.0,"pnl_B":0.0},{"closes":2,"cum_A":0.0,"cum_B":0.0,"hour_utc":"2026-04-25T15:00:00+00:00","pnl_A":0.0,"pnl_B":0.0},{"closes":2,"cum_A":0.0,"cum_B":0.0,"hour_utc":"2026-04-25T16:00:00+00:00","pnl_A":0.0,"pnl_B":0.0},{"closes":2,"cum_A":0.0,"cum_B":0.0,"hour_utc":"2026-04-25T17:00:00+00:00","pnl_A":0.0,"pnl_B":0.0},{"closes":2,"cum_A":0.0,"cum_B":0.0,"hour_utc":"2026-04-25T19:00:00+00:00","pnl_A":0.0,"pnl_B":0.0},{"closes":1,"cum_A":0.0,"cum_B":0.0,"hour_utc":"2026-04-25T23:00:00+00:00","pnl_A":0.0,"pnl_B":0.0},{"closes":7,"cum_A":0.0,"cum_B":0.0,"hour_utc":"2026-04-26T01:00:00+00:00","pnl_A":0.0,"pnl_B":0.0},{"closes":2,"cum_A":0.0,"cum_B":0.0,"hour_utc":"2026-04-26T02:00:00+00:00","pnl_A":0.0,"pnl_B":0.0},{"closes":3,"cum_A":0.0032,"cum_B":0.0,"hour_utc":"2026-04-26T04:00:00+00:00","pnl_A":0.0032,"pnl_B":0.0},{"closes":2,"cum_A":0.0032,"cum_B":0.0,"hour_utc":"2026-04-26T05:00:00+00:00","pnl_A":0.0,"pnl_B":0.0},{"closes":4,"cum_A":0.022,"cum_B":0.0,"hour_utc":"2026-04-26T06:00:00+00:00","pnl_A":0.0188,"pnl_B":0.0},{"closes":5,"cum_A":0.022,"cum_B":0.0055,"hour_utc":"2026-04-26T07:00:00+00:00","pnl_A":0.0,"pnl_B":0.0055},{"closes":23,"cum_A":0.1077,"cum_B":0.0576,"hour_utc":"2026-04-26T08:00:00+00:00","pnl_A":0.0857,"pnl_B":0.0521},{"closes":7,"cum_A":0.1077,"cum_B":0.0738,"hour_utc":"2026-04-26T09:00:00+00:00","pnl_A":0.0,"pnl_B":0.0162},{"closes":7,"cum_A":-0.3414,"cum_B":0.0869,"hour_utc":"2026-04-26T10:00:00+00:00","pnl_A":-0.4491,"pnl_B":0.0132},{"closes":4,"cum_A":-0.6801,"cum_B":0.0811,"hour_utc":"2026-04-26T11:00:00+00:00","pnl_A":-0.3387,"pnl_B":-0.0058},{"closes":10,"cum_A":-0.6652,"cum_B":0.0799,"hour_utc":"2026-04-26T12:00:00+00:00","pnl_A":0.0149,"pnl_B":-0.0012},{"closes":3,"cum_A":-0.6652,"cum_B":0.0488,"hour_utc":"2026-04-26T13:00:00+00:00","pnl_A":0.0,"pnl_B":-0.0311},{"closes":7,"cum_A":-0.6192,"cum_B":0.0461,"hour_utc":"2026-04-26T14:00:00+00:00","pnl_A":0.046,"pnl_B":-0.0027},{"closes":4,"cum_A":-0.4432,"cum_B":0.0461,"hour_utc":"2026-04-26T15:00:00+00:00","pnl_A":0.176,"pnl_B":0.0},{"closes":5,"cum_A":-0.9069,"cum_B":0.0419,"hour_utc":"2026-04-26T16:00:00+00:00","pnl_A":-0.4637,"pnl_B":-0.0042},{"closes":2,"cum_A":-0.8683,"cum_B":0.0419,"hour_utc":"2026-04-26T17:00:00+00:00","pnl_A":0.0386,"pnl_B":0.0},{"closes":2,"cum_A":-0.8472,"cum_B":0.0419,"hour_utc":"2026-04-26T18:00:00+00:00","pnl_A":0.0211,"pnl_B":0.0},{"closes":4,"cum_A":-0.8472,"cum_B":0.0388,"hour_utc":"2026-04-26T19:00:00+00:00","pnl_A":0.0,"pnl_B":-0.0031},{"closes":2,"cum_A":-0.372,"cum_B":0.0388,"hour_utc":"2026-04-26T20:00:00+00:00","pnl_A":0.4752,"pnl_B":0.0},{"closes":1,"cum_A":-0.3703,"cum_B":0.0388,"hour_utc":"2026-04-26T21:00:00+00:00","pnl_A":0.0017,"pnl_B":0.0},{"closes":7,"cum_A":-0.1009,"cum_B":998.3734,"hour_utc":"2026-04-26T22:00:00+00:00","pnl_A":0.2694,"pnl_B":998.3345},{"closes":3,"cum_A":-0.0282,"cum_B":998.3527,"hour_utc":"2026-04-26T23:00:00+00:00","pnl_A":0.0727,"pnl_B":-0.0207},{"closes":4,"cum_A":-0.3018,"cum_B":998.3502,"hour_utc":"2026-04-27T00:00:00+00:00","pnl_A":-0.2736,"pnl_B":-0.0024},{"closes":5,"cum_A":-0.3018,"cum_B":998.3351,"hour_utc":"2026-04-27T01:00:00+00:00","pnl_A":0.0,"pnl_B":-0.0152},{"closes":2,"cum_A":-0.3018,"cum_B":998.3191,"hour_utc":"2026-04-27T02:00:00+00:00","pnl_A":0.0,"pnl_B":-0.016},{"closes":5,"cum_A":-0.3018,"cum_B":998.3191,"hour_utc":"2026-04-27T03:00:00+00:00","pnl_A":0.0,"pnl_B":0.0},{"closes":4,"cum_A":-0.1975,"cum_B":998.3162,"hour_utc":"2026-04-27T04:00:00+00:00","pnl_A":0.1043,"pnl_B":-0.0029},{"closes":16,"cum_A":-4.7683,"cum_B":998.3163,"hour_utc":"2026-04-27T05:00:00+00:00","pnl_A":-4.5708,"pnl_B":0.0001},{"closes":8,"cum_A":-6.198,"cum_B":998.3163,"hour_utc":"2026-04-27T06:00:00+00:00","pnl_A":-1.4297,"pnl_B":0.0},{"closes":3,"cum_A":-5.5557,"cum_B":998.3163,"hour_utc":"2026-04-27T07:00:00+00:00","pnl_A":0.6423,"pnl_B":0.0},{"closes":11,"cum_A":-5.5557,"cum_B":998.5546,"hour_utc":"2026-04-27T08:00:00+00:00","pnl_A":0.0,"pnl_B":0.2383},{"closes":8,"cum_A":-5.5557,"cum_B":998.5674,"hour_utc":"2026-04-27T09:00:00+00:00","pnl_A":0.0,"pnl_B":0.0128},{"closes":12,"cum_A":-5.5557,"cum_B":998.607,"hour_utc":"2026-04-27T10:00:00+00:00","pnl_A":0.0,"pnl_B":0.0396},{"closes":21,"cum_A":-5.5557,"cum_B":998.7234,"hour_utc":"2026-04-27T11:00:00+00:00","pnl_A":0.0,"pnl_B":0.1164},{"closes":22,"cum_A":-5.5557,"cum_B":998.7517,"hour_utc":"2026-04-27T12:00:00+00:00","pnl_A":0.0,"pnl_B":0.0283},{"closes":29,"cum_A":-5.5557,"cum_B":998.7417,"hour_utc":"2026-04-27T13:00:00+00:00","pnl_A":0.0,"pnl_B":-0.01},{"closes":31,"cum_A":-5.5557,"cum_B":998.4785,"hour_utc":"2026-04-27T14:00:00+00:00","pnl_A":0.0,"pnl_B":-0.2632},{"closes":38,"cum_A":-5.5557,"cum_B":998.9807,"hour_utc":"2026-04-27T15:00:00+00:00","pnl_A":0.0,"pnl_B":0.5022},{"closes":12,"cum_A":-5.5557,"cum_B":998.9218,"hour_utc":"2026-04-27T16:00:00+00:00","pnl_A":0.0,"pnl_B":-0.0589},{"closes":18,"cum_A":-5.5557,"cum_B":998.1865,"hour_utc":"2026-04-27T17:00:00+00:00","pnl_A":0.0,"pnl_B":-0.7353},{"closes":8,"cum_A":-5.5557,"cum_B":997.5469,"hour_utc":"2026-04-27T18:00:00+00:00","pnl_A":0.0,"pnl_B":-0.6396},{"closes":27,"cum_A":-5.5557,"cum_B":997.5265,"hour_utc":"2026-04-27T19:00:00+00:00","pnl_A":0.0,"pnl_B":-0.0204},{"closes":9,"cum_A":-5.5557,"cum_B":996.954,"hour_utc":"2026-04-27T20:00:00+00:00","pnl_A":0.0,"pnl_B":-0.5725},{"closes":12,"cum_A":-5.5557,"cum_B":997.2524,"hour_utc":"2026-04-27T21:00:00+00:00","pnl_A":0.0,"pnl_B":0.2984},{"closes":12,"cum_A":-5.5557,"cum_B":997.2494,"hour_utc":"2026-04-27T22:00:00+00:00","pnl_A":0.0,"pnl_B":-0.003},{"closes":19,"cum_A":-5.5557,"cum_B":997.2301,"hour_utc":"2026-04-27T23:00:00+00:00","pnl_A":0.0,"pnl_B":-0.0193},{"closes":5,"cum_A":-5.5557,"cum_B":997.2273,"hour_utc":"2026-04-28T00:00:00+00:00","pnl_A":0.0,"pnl_B":-0.0028},{"closes":10,"cum_A":-5.5557,"cum_B":997.2189,"hour_utc":"2026-04-28T01:00:00+00:00","pnl_A":0.0,"pnl_B":-0.0084},{"closes":14,"cum_A":-5.5557,"cum_B":997.216,"hour_utc":"2026-04-28T02:00:00+00:00","pnl_A":0.0,"pnl_B":-0.0029},{"closes":1,"cum_A":-5.5557,"cum_B":997.216,"hour_utc":"2026-04-28T03:00:00+00:00","pnl_A":0.0,"pnl_B":0.0},{"closes":6,"cum_A":-5.5557,"cum_B":997.216,"hour_utc":"2026-04-28T04:00:00+00:00","pnl_A":0.0,"pnl_B":0.0},{"closes":3,"cum_A":-5.5557,"cum_B":998.736,"hour_utc":"2026-04-28T05:00:00+00:00","pnl_A":0.0,"pnl_B":1.52},{"closes":1,"cum_A":-5.5557,"cum_B":998.736,"hour_utc":"2026-04-28T06:00:00+00:00","pnl_A":0.0,"pnl_B":0.0},{"closes":23,"cum_A":-5.5557,"cum_B":998.8972,"hour_utc":"2026-04-28T07:00:00+00:00","pnl_A":0.0,"pnl_B":0.1613},{"closes":1,"cum_A":-5.5557,"cum_B":998.9165,"hour_utc":"2026-04-28T08:00:00+00:00","pnl_A":0.0,"pnl_B":0.0193},{"closes":14,"cum_A":-5.5557,"cum_B":998.9244,"hour_utc":"2026-04-28T09:00:00+00:00","pnl_A":0.0,"pnl_B":0.0079},{"closes":1,"cum_A":-5.5557,"cum_B":998.9244,"hour_utc":"2026-04-28T10:00:00+00:00","pnl_A":0.0,"pnl_B":0.0},{"closes":1,"cum_A":-5.5557,"cum_B":998.9255,"hour_utc":"2026-04-28T11:00:00+00:00","pnl_A":0.0,"pnl_B":0.0011},{"closes":1,"cum_A":-5.5557,"cum_B":998.9255,"hour_utc":"2026-04-28T13:00:00+00:00","pnl_A":0.0,"pnl_B":0.0},{"closes":5,"cum_A":-5.5557,"cum_B":998.929,"hour_utc":"2026-04-28T14:00:00+00:00","pnl_A":0.0,"pnl_B":0.0035},{"closes":3,"cum_A":-5.5557,"cum_B":997.5961,"hour_utc":"2026-04-28T15:00:00+00:00","pnl_A":0.0,"pnl_B":-1.3329},{"closes":11,"cum_A":-5.5557,"cum_B":997.5802,"hour_utc":"2026-04-28T16:00:00+00:00","pnl_A":0.0,"pnl_B":-0.0158},{"closes":4,"cum_A":-5.5557,"cum_B":996.9279,"hour_utc":"2026-04-28T17:00:00+00:00","pnl_A":0.0,"pnl_B":-0.6524},{"closes":6,"cum_A":-5.5557,"cum_B":996.2389,"hour_utc":"2026-04-28T18:00:00+00:00","pnl_A":0.0,"pnl_B":-0.6889},{"closes":1,"cum_A":-5.5557,"cum_B":996.2389,"hour_utc":"2026-04-28T19:00:00+00:00","pnl_A":0.0,"pnl_B":0.0},{"closes":1,"cum_A":-5.5557,"cum_B":996.2389,"hour_utc":"2026-04-28T20:00:00+00:00","pnl_A":0.0,"pnl_B":0.0},{"closes":3,"cum_A":-5.5557,"cum_B":996.2359,"hour_utc":"2026-04-28T21:00:00+00:00","pnl_A":0.0,"pnl_B":-0.003},{"closes":3,"cum_A":-5.5557,"cum_B":996.2259,"hour_utc":"2026-04-28T22:00:00+00:00","pnl_A":0.0,"pnl_B":-0.01},{"closes":2,"cum_A":-5.5557,"cum_B":996.2166,"hour_utc":"2026-04-28T23:00:00+00:00","pnl_A":0.0,"pnl_B":-0.0094},{"closes":1,"cum_A":-5.5557,"cum_B":996.2166,"hour_utc":"2026-04-29T00:00:00+00:00","pnl_A":0.0,"pnl_B":0.0},{"closes":1,"cum_A":-5.5557,"cum_B":996.2166,"hour_utc":"2026-04-29T01:00:00+00:00","pnl_A":0.0,"pnl_B":0.0},{"closes":1,"cum_A":-5.5557,"cum_B":996.2166,"hour_utc":"2026-04-29T02:00:00+00:00","pnl_A":0.0,"pnl_B":0.0},{"closes":4,"cum_A":-5.5557,"cum_B":996.2166,"hour_utc":"2026-04-29T03:00:00+00:00","pnl_A":0.0,"pnl_B":0.0},{"closes":1,"cum_A":-5.5557,"cum_B":996.2166,"hour_utc":"2026-04-29T04:00:00+00:00","pnl_A":0.0,"pnl_B":0.0},{"closes":5,"cum_A":-5.5557,"cum_B":996.2166,"hour_utc":"2026-04-29T06:00:00+00:00","pnl_A":0.0,"pnl_B":0.0},{"closes":1,"cum_A":-5.5557,"cum_B":996.2166,"hour_utc":"2026-04-29T08:00:00+00:00","pnl_A":0.0,"pnl_B":0.0},{"closes":1,"cum_A":-5.5557,"cum_B":996.2166,"hour_utc":"2026-04-29T09:00:00+00:00","pnl_A":0.0,"pnl_B":0.0},{"closes":1,"cum_A":-5.5557,"cum_B":996.2166,"hour_utc":"2026-04-29T10:00:00+00:00","pnl_A":0.0,"pnl_B":0.0},{"closes":2,"cum_A":-5.5557,"cum_B":996.2166,"hour_utc":"2026-04-29T11:00:00+00:00","pnl_A":0.0,"pnl_B":0.0},{"closes":3,"cum_A":-5.5557,"cum_B":996.2166,"hour_utc":"2026-04-29T13:00:00+00:00","pnl_A":0.0,"pnl_B":0.0},{"closes":2,"cum_A":-5.5557,"cum_B":996.2166,"hour_utc":"2026-04-29T14:00:00+00:00","pnl_A":0.0,"pnl_B":0.0},{"closes":2,"cum_A":-5.5557,"cum_B":996.2166,"hour_utc":"2026-04-29T15:00:00+00:00","pnl_A":0.0,"pnl_B":0.0},{"closes":3,"cum_A":-5.5557,"cum_B":996.2166,"hour_utc":"2026-04-30T00:00:00+00:00","pnl_A":0.0,"pnl_B":0.0},{"closes":13,"cum_A":-5.5557,"cum_B":996.2166,"hour_utc":"2026-04-30T02:00:00+00:00","pnl_A":0.0,"pnl_B":0.0},{"closes":14,"cum_A":-5.5557,"cum_B":996.2166,"hour_utc":"2026-04-30T03:00:00+00:00","pnl_A":0.0,"pnl_B":0.0},{"closes":21,"cum_A":-5.5557,"cum_B":996.234,"hour_utc":"2026-04-30T04:00:00+00:00","pnl_A":0.0,"pnl_B":0.0175},{"closes":5,"cum_A":-5.5557,"cum_B":995.5304,"hour_utc":"2026-04-30T05:00:00+00:00","pnl_A":0.0,"pnl_B":-0.7036},{"closes":7,"cum_A":-5.5557,"cum_B":995.639,"hour_utc":"2026-04-30T06:00:00+00:00","pnl_A":0.0,"pnl_B":0.1086},{"closes":19,"cum_A":-5.5557,"cum_B":994.0164,"hour_utc":"2026-04-30T07:00:00+00:00","pnl_A":0.0,"pnl_B":-1.6226},{"closes":10,"cum_A":-5.5557,"cum_B":992.8304,"hour_utc":"2026-04-30T08:00:00+00:00","pnl_A":0.0,"pnl_B":-1.186},{"closes":3,"cum_A":-5.5557,"cum_B":992.8304,"hour_utc":"2026-04-30T09:00:00+00:00","pnl_A":0.0,"pnl_B":0.0},{"closes":3,"cum_A":-5.5557,"cum_B":992.8304,"hour_utc":"2026-04-30T10:00:00+00:00","pnl_A":0.0,"pnl_B":0.0},{"closes":3,"cum_A":-5.5557,"cum_B":992.8304,"hour_utc":"2026-04-30T11:00:00+00:00","pnl_A":0.0,"pnl_B":0.0},{"closes":6,"cum_A":-5.5557,"cum_B":992.8163,"hour_utc":"2026-04-30T12:00:00+00:00","pnl_A":0.0,"pnl_B":-0.0142},{"closes":6,"cum_A":-5.5557,"cum_B":992.8231,"hour_utc":"2026-04-30T13:00:00+00:00","pnl_A":0.0,"pnl_B":0.0068},{"closes":3,"cum_A":-5.5557,"cum_B":992.99,"hour_utc":"2026-04-30T15:00:00+00:00","pnl_A":0.0,"pnl_B":0.1669},{"closes":3,"cum_A":-5.5557,"cum_B":993.0208,"hour_utc":"2026-04-30T20:00:00+00:00","pnl_A":0.0,"pnl_B":0.0308},{"closes":9,"cum_A":-5.5557,"cum_B":992.9926,"hour_utc":"2026-04-30T21:00:00+00:00","pnl_A":0.0,"pnl_B":-0.0282},{"closes":6,"cum_A":-5.5557,"cum_B":992.9158,"hour_utc":"2026-04-30T22:00:00+00:00","pnl_A":0.0,"pnl_B":-0.0768},{"closes":4,"cum_A":-5.5557,"cum_B":992.895,"hour_utc":"2026-04-30T23:00:00+00:00","pnl_A":0.0,"pnl_B":-0.0208},{"closes":5,"cum_A":-5.5557,"cum_B":992.8838,"hour_utc":"2026-05-01T00:00:00+00:00","pnl_A":0.0,"pnl_B":-0.0112},{"closes":1,"cum_A":-5.5557,"cum_B":992.8825,"hour_utc":"2026-05-01T01:00:00+00:00","pnl_A":0.0,"pnl_B":-0.0013},{"closes":5,"cum_A":-5.5557,"cum_B":993.557,"hour_utc":"2026-05-01T02:00:00+00:00","pnl_A":0.0,"pnl_B":0.6745},{"closes":5,"cum_A":-5.5557,"cum_B":993.3344,"hour_utc":"2026-05-01T03:00:00+00:00","pnl_A":0.0,"pnl_B":-0.2226},{"closes":1,"cum_A":-5.5557,"cum_B":993.4641,"hour_utc":"2026-05-01T04:00:00+00:00","pnl_A":0.0,"pnl_B":0.1297},{"closes":3,"cum_A":-5.5557,"cum_B":993.4678,"hour_utc":"2026-05-01T05:00:00+00:00","pnl_A":0.0,"pnl_B":0.0037},{"closes":3,"cum_A":-5.5557,"cum_B":993.5637,"hour_utc":"2026-05-01T07:00:00+00:00","pnl_A":0.0,"pnl_B":0.0959},{"closes":1,"cum_A":-5.5557,"cum_B":993.3082,"hour_utc":"2026-05-01T08:00:00+00:00","pnl_A":0.0,"pnl_B":-0.2555},{"closes":19,"cum_A":-5.5557,"cum_B":993.2564,"hour_utc":"2026-05-01T09:00:00+00:00","pnl_A":0.0,"pnl_B":-0.0518},{"closes":64,"cum_A":-5.5557,"cum_B":993.2564,"hour_utc":"2026-05-01T10:00:00+00:00","pnl_A":0.0,"pnl_B":0.0},{"closes":1,"cum_A":-5.5557,"cum_B":993.9689,"hour_utc":"2026-05-01T12:00:00+00:00","pnl_A":0.0,"pnl_B":0.7125}],"hours_back":168,"now_utc":"2026-05-01T14:07:05+00:00","recent_deploys":[],"rows_in_window":899,"system_cutover":{"system_A":{"last_flip_pos_to_neg_iso":"2026-04-27T13:00:00+00:00","last_flip_pos_to_neg_ts":1777294800},"system_B":{"last_flip_pos_to_neg_iso":"2026-05-01T09:00:00+00:00","last_flip_pos_to_neg_ts":1777626000}},"total_rows":975,"verdict_summary":["System A: 6h=+0.0000 (n=0), 12h=+0.0000 (n=0), 24h=+0.0000 (n=0), 48h=+0.0000 (n=0)","System B: 6h=+0.4052 (n=30), 12h=+1.0865 (n=42), 24h=+1.1459 (n=68), 48h=-2.2476 (n=160)"]}
,
  "edge_audit_pivot": {"by_close_reason":[{"avg_mae_pct":-0.9077,"avg_mfe_pct":0.9375,"close_reason":"exchange_fill","losses":3,"mean_pnl_lcb_usd":-0.2174,"mean_pnl_usd":-0.0556,"n":17,"recommended_keep":false,"sum_pnl_usd":-0.9454,"wilson_wr_lcb_pct":51.3,"wins":9,"wr_pct":75.0}],"by_coin":[{"avg_mae_pct":-1.7267,"avg_mfe_pct":1.0423,"coin":"RSR","losses":1,"mean_pnl_lcb_usd":-0.3937,"mean_pnl_usd":-0.0913,"n":3,"recommended_keep":false,"sum_pnl_usd":-0.2738,"wilson_wr_lcb_pct":25.4,"wins":2,"wr_pct":66.7},{"avg_mae_pct":-0.3986,"avg_mfe_pct":0.8173,"coin":"GRASS","losses":0,"mean_pnl_lcb_usd":0.0067,"mean_pnl_usd":0.0186,"n":2,"recommended_keep":false,"sum_pnl_usd":0.0373,"wilson_wr_lcb_pct":42.5,"wins":2,"wr_pct":100.0},{"avg_mae_pct":-0.6518,"avg_mfe_pct":0.8547,"coin":"INJ","losses":0,"mean_pnl_lcb_usd":-0.006,"mean_pnl_usd":0.0093,"n":2,"recommended_keep":false,"sum_pnl_usd":0.0186,"wilson_wr_lcb_pct":27.0,"wins":1,"wr_pct":100.0},{"avg_mae_pct":-1.1174,"avg_mfe_pct":0.3539,"coin":"NOT","losses":1,"mean_pnl_lcb_usd":-1.8963,"mean_pnl_usd":-0.7169,"n":2,"recommended_keep":false,"sum_pnl_usd":-1.4339,"wilson_wr_lcb_pct":0.0,"wins":0,"wr_pct":0.0},{"avg_mae_pct":null,"avg_mfe_pct":null,"coin":"ICP","losses":0,"mean_pnl_lcb_usd":null,"mean_pnl_usd":0.045,"n":1,"recommended_keep":false,"sum_pnl_usd":0.045,"wilson_wr_lcb_pct":27.0,"wins":1,"wr_pct":100.0},{"avg_mae_pct":null,"avg_mfe_pct":null,"coin":"HBAR","losses":1,"mean_pnl_lcb_usd":null,"mean_pnl_usd":-0.0003,"n":1,"recommended_keep":false,"sum_pnl_usd":-0.0003,"wilson_wr_lcb_pct":0.0,"wins":0,"wr_pct":0.0},{"avg_mae_pct":-0.3437,"avg_mfe_pct":0.5912,"coin":"UMA","losses":0,"mean_pnl_lcb_usd":null,"mean_pnl_usd":0.0,"n":1,"recommended_keep":false,"sum_pnl_usd":0.0,"wilson_wr_lcb_pct":0,"wins":0,"wr_pct":null},{"avg_mae_pct":-0.3021,"avg_mfe_pct":0.9819,"coin":"STRK","losses":0,"mean_pnl_lcb_usd":null,"mean_pnl_usd":0.0194,"n":1,"recommended_keep":false,"sum_pnl_usd":0.0194,"wilson_wr_lcb_pct":27.0,"wins":1,"wr_pct":100.0},{"avg_mae_pct":-0.0937,"avg_mfe_pct":1.4497,"coin":"CC","losses":0,"mean_pnl_lcb_usd":null,"mean_pnl_usd":0.0,"n":1,"recommended_keep":false,"sum_pnl_usd":0.0,"wilson_wr_lcb_pct":0,"wins":0,"wr_pct":null},{"avg_mae_pct":-0.6194,"avg_mfe_pct":0.8446,"coin":"PUMP","losses":0,"mean_pnl_lcb_usd":null,"mean_pnl_usd":0.0124,"n":1,"recommended_keep":false,"sum_pnl_usd":0.0124,"wilson_wr_lcb_pct":27.0,"wins":1,"wr_pct":100.0},{"avg_mae_pct":-0.24,"avg_mfe_pct":2.5875,"coin":"JUP","losses":0,"mean_pnl_lcb_usd":null,"mean_pnl_usd":0.6299,"n":1,"recommended_keep":false,"sum_pnl_usd":0.6299,"wilson_wr_lcb_pct":27.0,"wins":1,"wr_pct":100.0},{"avg_mae_pct":-2.5001,"avg_mfe_pct":0.4293,"coin":"STABLE","losses":0,"mean_pnl_lcb_usd":null,"mean_pnl_usd":0.0,"n":1,"recommended_keep":false,"sum_pnl_usd":0.0,"wilson_wr_lcb_pct":0,"wins":0,"wr_pct":null}],"by_hour_utc":[{"avg_mae_pct":-1.3037,"avg_mfe_pct":0.6338,"hour_utc":0,"losses":0,"mean_pnl_lcb_usd":null,"mean_pnl_usd":0.0186,"n":1,"recommended_keep":false,"sum_pnl_usd":0.0186,"wilson_wr_lcb_pct":27.0,"wins":1,"wr_pct":100.0},{"avg_mae_pct":-0.0937,"avg_mfe_pct":1.4497,"hour_utc":3,"losses":0,"mean_pnl_lcb_usd":null,"mean_pnl_usd":0.0,"n":1,"recommended_keep":false,"sum_pnl_usd":0.0,"wilson_wr_lcb_pct":0,"wins":0,"wr_pct":null},{"avg_mae_pct":-0.4909,"avg_mfe_pct":0.8917,"hour_utc":5,"losses":0,"mean_pnl_lcb_usd":0.0,"mean_pnl_usd":0.0,"n":2,"recommended_keep":false,"sum_pnl_usd":0.0,"wilson_wr_lcb_pct":0,"wins":0,"wr_pct":null},{"avg_mae_pct":-1.2531,"avg_mfe_pct":0.0,"hour_utc":6,"losses":1,"mean_pnl_lcb_usd":null,"mean_pnl_usd":-1.4339,"n":1,"recommended_keep":false,"sum_pnl_usd":-1.4339,"wilson_wr_lcb_pct":0.0,"wins":0,"wr_pct":0.0},{"avg_mae_pct":-0.4297,"avg_mfe_pct":1.716,"hour_utc":7,"losses":0,"mean_pnl_lcb_usd":-0.1867,"mean_pnl_usd":0.3211,"n":2,"recommended_keep":false,"sum_pnl_usd":0.6423,"wilson_wr_lcb_pct":42.5,"wins":2,"wr_pct":100.0},{"avg_mae_pct":null,"avg_mfe_pct":null,"hour_utc":8,"losses":1,"mean_pnl_lcb_usd":-0.0149,"mean_pnl_usd":0.0223,"n":2,"recommended_keep":false,"sum_pnl_usd":0.0447,"wilson_wr_lcb_pct":12.1,"wins":1,"wr_pct":50.0},{"avg_mae_pct":-2.5001,"avg_mfe_pct":0.4293,"hour_utc":9,"losses":0,"mean_pnl_lcb_usd":null,"mean_pnl_usd":0.0,"n":1,"recommended_keep":false,"sum_pnl_usd":0.0,"wilson_wr_lcb_pct":0,"wins":0,"wr_pct":null},{"avg_mae_pct":-3.8117,"avg_mfe_pct":0.0,"hour_utc":10,"losses":1,"mean_pnl_lcb_usd":null,"mean_pnl_usd":-0.4498,"n":1,"recommended_keep":false,"sum_pnl_usd":-0.4498,"wilson_wr_lcb_pct":0.0,"wins":0,"wr_pct":0.0},{"avg_mae_pct":-0.5037,"avg_mfe_pct":0.7966,"hour_utc":14,"losses":0,"mean_pnl_lcb_usd":null,"mean_pnl_usd":0.0259,"n":1,"recommended_keep":false,"sum_pnl_usd":0.0259,"wilson_wr_lcb_pct":27.0,"wins":1,"wr_pct":100.0},{"avg_mae_pct":-0.6842,"avg_mfe_pct":1.5634,"hour_utc":15,"losses":0,"mean_pnl_lcb_usd":-0.0285,"mean_pnl_usd":0.088,"n":2,"recommended_keep":false,"sum_pnl_usd":0.176,"wilson_wr_lcb_pct":42.5,"wins":2,"wr_pct":100.0},{"avg_mae_pct":-0.3437,"avg_mfe_pct":0.5912,"hour_utc":16,"losses":0,"mean_pnl_lcb_usd":null,"mean_pnl_usd":0.0,"n":1,"recommended_keep":false,"sum_pnl_usd":0.0,"wilson_wr_lcb_pct":0,"wins":0,"wr_pct":null},{"avg_mae_pct":-0.2936,"avg_mfe_pct":0.8381,"hour_utc":17,"losses":0,"mean_pnl_lcb_usd":null,"mean_pnl_usd":0.0114,"n":1,"recommended_keep":false,"sum_pnl_usd":0.0114,"wilson_wr_lcb_pct":27.0,"wins":1,"wr_pct":100.0},{"avg_mae_pct":-0.3021,"avg_mfe_pct":0.9819,"hour_utc":22,"losses":0,"mean_pnl_lcb_usd":null,"mean_pnl_usd":0.0194,"n":1,"recommended_keep":false,"sum_pnl_usd":0.0194,"wilson_wr_lcb_pct":27.0,"wins":1,"wr_pct":100.0}],"by_regime":[{"avg_mae_pct":-0.5767,"avg_mfe_pct":1.014,"losses":0,"mean_pnl_lcb_usd":0.0005,"mean_pnl_usd":0.0279,"n":9,"recommended_keep":true,"regime":"chop","sum_pnl_usd":0.2513,"wilson_wr_lcb_pct":68.9,"wins":6,"wr_pct":100.0},{"avg_mae_pct":-0.9225,"avg_mfe_pct":0.9874,"losses":1,"mean_pnl_lcb_usd":-0.7195,"mean_pnl_usd":-0.1583,"n":5,"recommended_keep":false,"regime":"bear-calm","sum_pnl_usd":-0.7916,"wilson_wr_lcb_pct":25.4,"wins":2,"wr_pct":66.7},{"avg_mae_pct":-3.8117,"avg_mfe_pct":0.0,"losses":2,"mean_pnl_lcb_usd":-0.3948,"mean_pnl_usd":-0.135,"n":3,"recommended_keep":false,"regime":"unknown","sum_pnl_usd":-0.4051,"wilson_wr_lcb_pct":7.8,"wins":1,"wr_pct":33.3}],"by_side":[{"avg_mae_pct":-1.0169,"avg_mfe_pct":0.8947,"losses":3,"mean_pnl_lcb_usd":-0.2481,"mean_pnl_usd":-0.0643,"n":15,"recommended_keep":false,"side":"SELL","sum_pnl_usd":-0.9648,"wilson_wr_lcb_pct":47.9,"wins":8,"wr_pct":72.7},{"avg_mae_pct":-0.1979,"avg_mfe_pct":1.2158,"losses":0,"mean_pnl_lcb_usd":-0.0063,"mean_pnl_usd":0.0097,"n":2,"recommended_keep":false,"side":"BUY","sum_pnl_usd":0.0194,"wilson_wr_lcb_pct":27.0,"wins":1,"wr_pct":100.0}],"days":14,"discouraged_coins_with_data":["RSR"],"engine":"PIVOT","err":null,"mfe_distribution":{">=100bp":{"n":4,"pct":23.5},">=10bp":{"n":13,"pct":76.5},">=20bp":{"n":13,"pct":76.5},">=30bp":{"n":13,"pct":76.5},">=50bp":{"n":12,"pct":70.6},">=5bp":{"n":13,"pct":76.5}},"min_n":3,"overall":{"avg_mae_pct":-0.9077,"avg_mfe_pct":0.9375,"engine":"PIVOT","losses":3,"mean_pnl_lcb_usd":-0.2174,"mean_pnl_usd":-0.0556,"n":17,"recommended_keep":false,"sum_pnl_usd":-0.9454,"wilson_wr_lcb_pct":51.3,"wins":9,"wr_pct":75.0},"recommended_coin_allowlist":[],"sample_recent_trades":[{"close_reason":"exchange_fill","coin":"STABLE","engine":"PIVOT","hour_utc":9,"iso":"2026-04-27T09:42:38+00:00","mae_pct":-0.025001460365675642,"mfe_pct":0.00429347508616141,"pnl":0.0,"regime":"bear-calm","side":"SELL","ts":1777282958},{"close_reason":"exchange_fill","coin":"JUP","engine":"PIVOT","hour_utc":7,"iso":"2026-04-27T07:50:22+00:00","mae_pct":-0.002400232110357836,"mfe_pct":0.02587502967319927,"pnl":0.6299,"regime":"bear-calm","side":"SELL","ts":1777276222},{"close_reason":"exchange_fill","coin":"PUMP","engine":"PIVOT","hour_utc":7,"iso":"2026-04-27T07:50:13+00:00","mae_pct":-0.006193693693693661,"mfe_pct":0.008445945945945967,"pnl":0.0124,"regime":"bear-calm","side":"SELL","ts":1777276213},{"close_reason":"exchange_fill","coin":"NOT","engine":"PIVOT","hour_utc":6,"iso":"2026-04-27T06:55:16+00:00","mae_pct":-0.012531328320802037,"mfe_pct":0.0,"pnl":-1.4339,"regime":"bear-calm","side":"SELL","ts":1777272916},{"close_reason":"exchange_fill","coin":"INJ","engine":"PIVOT","hour_utc":5,"iso":"2026-04-27T05:33:56+00:00","mae_pct":0.0,"mfe_pct":0.010756065007458621,"pnl":0.0,"regime":"bear-calm","side":"SELL","ts":1777268036},{"close_reason":"exchange_fill","coin":"NOT","engine":"PIVOT","hour_utc":5,"iso":"2026-04-27T05:21:35+00:00","mae_pct":-0.009817351598173507,"mfe_pct":0.0070776255707763035,"pnl":-0.0,"regime":"chop","side":"SELL","ts":1777267295},{"close_reason":"exchange_fill","coin":"CC","engine":"PIVOT","hour_utc":3,"iso":"2026-04-27T03:10:44+00:00","mae_pct":-0.0009374581491897766,"mfe_pct":0.014497120664256062,"pnl":0.0,"regime":"chop","side":"BUY","ts":1777259444},{"close_reason":"exchange_fill","coin":"INJ","engine":"PIVOT","hour_utc":0,"iso":"2026-04-27T00:17:07+00:00","mae_pct":-0.013036850831684247,"mfe_pct":0.006337915173557211,"pnl":0.0186,"regime":"chop","side":"SELL","ts":1777249027},{"close_reason":"exchange_fill","coin":"STRK","engine":"PIVOT","hour_utc":22,"iso":"2026-04-26T22:33:54+00:00","mae_pct":-0.0030211480362536533,"mfe_pct":0.009818731117824811,"pnl":0.0194,"regime":"chop","side":"BUY","ts":1777242834},{"close_reason":"exchange_fill","coin":"GRASS","engine":"PIVOT","hour_utc":17,"iso":"2026-04-26T17:20:45+00:00","mae_pct":-0.002935916940240718,"mfe_pct":0.008380708356687154,"pnl":0.0114,"regime":"chop","side":"SELL","ts":1777224045}],"target_wr_lcb_pct":55.00000000000001,"total_rows_engine":17,"z":1.645}
,
  "edge_audit_overall": {"days":7,"engine":null,"engines":[{"avg_mae_pct":-0.5048,"avg_mfe_pct":0.458,"engine":"CONFLUENCE_BTC_WALL+SNIPER","losses":27,"mean_pnl_lcb_usd":-0.031,"mean_pnl_usd":-0.0093,"n":71,"recommended_keep":false,"sum_pnl_usd":-0.6604,"top_coins":[{"avg_mae_pct":-0.2334,"avg_mfe_pct":0.2918,"coin":"W","losses":0,"mean_pnl_lcb_usd":-0.0001,"mean_pnl_usd":0.0001,"n":6,"recommended_keep":false,"sum_pnl_usd":0.0009,"wilson_wr_lcb_pct":42.5,"wins":2,"wr_pct":100.0},{"avg_mae_pct":-0.2315,"avg_mfe_pct":0.9483,"coin":"HBAR","losses":1,"mean_pnl_lcb_usd":-0.0019,"mean_pnl_usd":0.0036,"n":5,"recommended_keep":false,"sum_pnl_usd":0.018,"wilson_wr_lcb_pct":25.4,"wins":2,"wr_pct":66.7},{"avg_mae_pct":-0.6683,"avg_mfe_pct":0.1066,"coin":"S","losses":3,"mean_pnl_lcb_usd":-0.0089,"mean_pnl_usd":-0.0041,"n":5,"recommended_keep":false,"sum_pnl_usd":-0.0207,"wilson_wr_lcb_pct":0.0,"wins":0,"wr_pct":0.0},{"avg_mae_pct":-0.7147,"avg_mfe_pct":0.1972,"coin":"TURBO","losses":3,"mean_pnl_lcb_usd":-0.3443,"mean_pnl_usd":-0.133,"n":5,"recommended_keep":false,"sum_pnl_usd":-0.6648,"wilson_wr_lcb_pct":0.0,"wins":0,"wr_pct":0.0},{"avg_mae_pct":-0.2825,"avg_mfe_pct":0.1742,"coin":"TRB","losses":1,"mean_pnl_lcb_usd":-0.0031,"mean_pnl_usd":0.0023,"n":4,"recommended_keep":false,"sum_pnl_usd":0.0092,"wilson_wr_lcb_pct":12.1,"wins":1,"wr_pct":50.0}],"wilson_wr_lcb_pct":27.6,"wins":17,"wr_pct":38.6},{"avg_mae_pct":-0.4623,"avg_mfe_pct":0.3909,"engine":"CONFLUENCE_BTC_WALL+NEWS","losses":30,"mean_pnl_lcb_usd":-0.0564,"mean_pnl_usd":-0.0268,"n":64,"recommended_keep":false,"sum_pnl_usd":-1.7153,"top_coins":[{"avg_mae_pct":-0.3916,"avg_mfe_pct":0.2844,"coin":"ANIME","losses":2,"mean_pnl_lcb_usd":-0.0015,"mean_pnl_usd":-0.0001,"n":5,"recommended_keep":false,"sum_pnl_usd":-0.0007,"wilson_wr_lcb_pct":18.2,"wins":2,"wr_pct":50.0},{"avg_mae_pct":-0.7681,"avg_mfe_pct":0.4438,"coin":"LINEA","losses":1,"mean_pnl_lcb_usd":-0.0104,"mean_pnl_usd":-0.0039,"n":4,"recommended_keep":false,"sum_pnl_usd":-0.0157,"wilson_wr_lcb_pct":0.0,"wins":0,"wr_pct":0.0},{"avg_mae_pct":-0.6498,"avg_mfe_pct":0.2499,"coin":"IP","losses":2,"mean_pnl_lcb_usd":-0.0121,"mean_pnl_usd":0.014,"n":4,"recommended_keep":false,"sum_pnl_usd":0.0561,"wilson_wr_lcb_pct":18.2,"wins":2,"wr_pct":50.0},{"avg_mae_pct":null,"avg_mfe_pct":null,"coin":"STABLE","losses":1,"mean_pnl_lcb_usd":-0.0001,"mean_pnl_usd":-0.0,"n":3,"recommended_keep":false,"sum_pnl_usd":-0.0001,"wilson_wr_lcb_pct":0.0,"wins":0,"wr_pct":0.0},{"avg_mae_pct":-0.651,"avg_mfe_pct":0.2737,"coin":"BIGTIME","losses":1,"mean_pnl_lcb_usd":-0.0019,"mean_pnl_usd":0.0003,"n":3,"recommended_keep":false,"sum_pnl_usd":0.0009,"wilson_wr_lcb_pct":25.4,"wins":2,"wr_pct":66.7}],"wilson_wr_lcb_pct":29.4,"wins":20,"wr_pct":40.0},{"avg_mae_pct":-0.4953,"avg_mfe_pct":0.5948,"engine":"CONFLUENCE_BTC_WALL+OBI","losses":20,"mean_pnl_lcb_usd":-0.0395,"mean_pnl_usd":-0.0165,"n":56,"recommended_keep":false,"sum_pnl_usd":-0.9262,"top_coins":[{"avg_mae_pct":-0.4903,"avg_mfe_pct":0.3493,"coin":"OP","losses":3,"mean_pnl_lcb_usd":-0.0017,"mean_pnl_usd":-0.0007,"n":10,"recommended_keep":false,"sum_pnl_usd":-0.0071,"wilson_wr_lcb_pct":22.1,"wins":3,"wr_pct":50.0},{"avg_mae_pct":-0.9673,"avg_mfe_pct":0.3926,"coin":"WIF","losses":4,"mean_pnl_lcb_usd":-0.0189,"mean_pnl_usd":-0.0084,"n":8,"recommended_keep":false,"sum_pnl_usd":-0.0671,"wilson_wr_lcb_pct":0.0,"wins":0,"wr_pct":0.0},{"avg_mae_pct":-0.5646,"avg_mfe_pct":0.3863,"coin":"MEW","losses":1,"mean_pnl_lcb_usd":-0.0014,"mean_pnl_usd":0.0007,"n":7,"recommended_keep":false,"sum_pnl_usd":0.0047,"wilson_wr_lcb_pct":12.1,"wins":1,"wr_pct":50.0},{"avg_mae_pct":-0.1135,"avg_mfe_pct":0.6541,"coin":"INJ","losses":1,"mean_pnl_lcb_usd":0.0067,"mean_pnl_usd":0.0317,"n":7,"recommended_keep":false,"sum_pnl_usd":0.2218,"wilson_wr_lcb_pct":49.8,"wins":5,"wr_pct":83.3},{"avg_mae_pct":-0.0507,"avg_mfe_pct":1.8487,"coin":"NOT","losses":1,"mean_pnl_lcb_usd":-0.0958,"mean_pnl_usd":-0.0292,"n":6,"recommended_keep":false,"sum_pnl_usd":-0.1751,"wilson_wr_lcb_pct":35.6,"wins":3,"wr_pct":75.0}],"wilson_wr_lcb_pct":31.7,"wins":16,"wr_pct":44.4},{"avg_mae_pct":-0.775,"avg_mfe_pct":6239.8918,"engine":"CONFLUENCE_SNIPER","losses":18,"mean_pnl_lcb_usd":-17.4048,"mean_pnl_usd":26.9807,"n":37,"recommended_keep":false,"sum_pnl_usd":998.2867,"top_coins":[{"avg_mae_pct":null,"avg_mfe_pct":null,"coin":"ASTER","losses":2,"mean_pnl_lcb_usd":-0.0013,"mean_pnl_usd":-0.0006,"n":3,"recommended_keep":false,"sum_pnl_usd":-0.0018,"wilson_wr_lcb_pct":0.0,"wins":0,"wr_pct":0.0},{"avg_mae_pct":0.0,"avg_mfe_pct":0.272,"coin":"ETC","losses":0,"mean_pnl_lcb_usd":-0.018,"mean_pnl_usd":0.0289,"n":3,"recommended_keep":false,"sum_pnl_usd":0.0867,"wilson_wr_lcb_pct":42.5,"wins":2,"wr_pct":100.0},{"avg_mae_pct":-1.237,"avg_mfe_pct":0.1307,"coin":"ETHFI","losses":2,"mean_pnl_lcb_usd":-0.0854,"mean_pnl_usd":-0.0331,"n":3,"recommended_keep":false,"sum_pnl_usd":-0.0994,"wilson_wr_lcb_pct":0.0,"wins":0,"wr_pct":0.0},{"avg_mae_pct":-1.519,"avg_mfe_pct":0.0,"coin":"SNX","losses":2,"mean_pnl_lcb_usd":-0.0134,"mean_pnl_usd":-0.0051,"n":3,"recommended_keep":false,"sum_pnl_usd":-0.0153,"wilson_wr_lcb_pct":0.0,"wins":0,"wr_pct":0.0},{"avg_mae_pct":null,"avg_mfe_pct":null,"coin":"ZK","losses":1,"mean_pnl_lcb_usd":-0.0153,"mean_pnl_usd":-0.0058,"n":2,"recommended_keep":false,"sum_pnl_usd":-0.0116,"wilson_wr_lcb_pct":0.0,"wins":0,"wr_pct":0.0}],"wilson_wr_lcb_pct":18.3,"wins":8,"wr_pct":30.8},{"avg_mae_pct":-0.639,"avg_mfe_pct":0.4463,"engine":"CONFLUENCE_BTC_WALL+DAY+SNIPER","losses":11,"mean_pnl_lcb_usd":-0.0028,"mean_pnl_usd":0.0022,"n":28,"recommended_keep":false,"sum_pnl_usd":0.0617,"top_coins":[{"avg_mae_pct":-0.0962,"avg_mfe_pct":0.6611,"coin":"CC","losses":0,"mean_pnl_lcb_usd":-0.0088,"mean_pnl_usd":0.0158,"n":5,"recommended_keep":false,"sum_pnl_usd":0.0788,"wilson_wr_lcb_pct":52.6,"wins":3,"wr_pct":100.0},{"avg_mae_pct":-0.2504,"avg_mfe_pct":0.4899,"coin":"SEI","losses":2,"mean_pnl_lcb_usd":-0.0033,"mean_pnl_usd":-0.0013,"n":4,"recommended_keep":false,"sum_pnl_usd":-0.0051,"wilson_wr_lcb_pct":0.0,"wins":0,"wr_pct":0.0},{"avg_mae_pct":0.0,"avg_mfe_pct":1.5038,"coin":"SUSHI","losses":0,"mean_pnl_lcb_usd":-0.0032,"mean_pnl_usd":0.005,"n":3,"recommended_keep":false,"sum_pnl_usd":0.0151,"wilson_wr_lcb_pct":42.5,"wins":2,"wr_pct":100.0},{"avg_mae_pct":-0.6144,"avg_mfe_pct":0.1839,"coin":"LTC","losses":2,"mean_pnl_lcb_usd":-0.0073,"mean_pnl_usd":-0.003,"n":3,"recommended_keep":false,"sum_pnl_usd":-0.009,"wilson_wr_lcb_pct":7.8,"wins":1,"wr_pct":33.3},{"avg_mae_pct":-0.5583,"avg_mfe_pct":0.3565,"coin":"STX","losses":1,"mean_pnl_lcb_usd":-0.0045,"mean_pnl_usd":-0.0005,"n":2,"recommended_keep":false,"sum_pnl_usd":-0.0011,"wilson_wr_lcb_pct":12.1,"wins":1,"wr_pct":50.0}],"wilson_wr_lcb_pct":33.5,"wins":11,"wr_pct":50.0},{"avg_mae_pct":-1.1033,"avg_mfe_pct":1.1889,"engine":"FUNDING_MR","losses":4,"mean_pnl_lcb_usd":-0.1993,"mean_pnl_usd":-0.0922,"n":20,"recommended_keep":false,"sum_pnl_usd":-1.8442,"top_coins":[{"avg_mae_pct":-1.1917,"avg_mfe_pct":1.485,"coin":"STABLE","losses":1,"mean_pnl_lcb_usd":-0.2575,"mean_pnl_usd":-0.0969,"n":3,"recommended_keep":false,"sum_pnl_usd":-0.2907,"wilson_wr_lcb_pct":25.4,"wins":2,"wr_pct":66.7},{"avg_mae_pct":-1.0926,"avg_mfe_pct":0.638,"coin":"BLAST","losses":1,"mean_pnl_lcb_usd":-0.551,"mean_pnl_usd":-0.2017,"n":3,"recommended_keep":false,"sum_pnl_usd":-0.6051,"wilson_wr_lcb_pct":12.1,"wins":1,"wr_pct":50.0},{"avg_mae_pct":-1.1871,"avg_mfe_pct":0.9925,"coin":"APE","losses":0,"mean_pnl_lcb_usd":-0.0006,"mean_pnl_usd":0.0091,"n":2,"recommended_keep":false,"sum_pnl_usd":0.0181,"wilson_wr_lcb_pct":42.5,"wins":2,"wr_pct":100.0},{"avg_mae_pct":-1.3475,"avg_mfe_pct":1.513,"coin":"NOT","losses":0,"mean_pnl_lcb_usd":-0.0336,"mean_pnl_usd":0.0522,"n":2,"recommended_keep":false,"sum_pnl_usd":0.1043,"wilson_wr_lcb_pct":27.0,"wins":1,"wr_pct":100.0},{"avg_mae_pct":-2.8076,"avg_mfe_pct":0.0,"coin":"JTO","losses":1,"mean_pnl_lcb_usd":-0.4502,"mean_pnl_usd":-0.1658,"n":2,"recommended_keep":false,"sum_pnl_usd":-0.3317,"wilson_wr_lcb_pct":12.1,"wins":1,"wr_pct":50.0}],"wilson_wr_lcb_pct":46.5,"wins":9,"wr_pct":69.2},{"avg_mae_pct":-0.4717,"avg_mfe_pct":0.4082,"engine":"CONFLUENCE_BTC_WALL+DAY","losses":9,"mean_pnl_lcb_usd":-0.0793,"mean_pnl_usd":-0.0255,"n":20,"recommended_keep":false,"sum_pnl_usd":-0.51,"top_coins":[{"avg_mae_pct":-0.0743,"avg_mfe_pct":0.5958,"coin":"PROVE","losses":1,"mean_pnl_lcb_usd":-0.0005,"mean_pnl_usd":0.0006,"n":4,"recommended_keep":false,"sum_pnl_usd":0.0024,"wilson_wr_lcb_pct":25.4,"wins":2,"wr_pct":66.7},{"avg_mae_pct":-0.4556,"avg_mfe_pct":0.7947,"coin":"WLFI","losses":0,"mean_pnl_lcb_usd":-0.0034,"mean_pnl_usd":0.0053,"n":3,"recommended_keep":false,"sum_pnl_usd":0.016,"wilson_wr_lcb_pct":42.5,"wins":2,"wr_pct":100.0},{"avg_mae_pct":-0.3307,"avg_mfe_pct":0.1907,"coin":"TRX","losses":0,"mean_pnl_lcb_usd":-0.0002,"mean_pnl_usd":0.0003,"n":3,"recommended_keep":false,"sum_pnl_usd":0.001,"wilson_wr_lcb_pct":27.0,"wins":1,"wr_pct":100.0},{"avg_mae_pct":-0.5228,"avg_mfe_pct":0.6622,"coin":"APE","losses":2,"mean_pnl_lcb_usd":-0.0376,"mean_pnl_usd":0.0378,"n":3,"recommended_keep":false,"sum_pnl_usd":0.1134,"wilson_wr_lcb_pct":7.8,"wins":1,"wr_pct":33.3},{"avg_mae_pct":-0.4889,"avg_mfe_pct":0.018,"coin":"BNB","losses":2,"mean_pnl_lcb_usd":-0.003,"mean_pnl_usd":-0.0029,"n":2,"recommended_keep":false,"sum_pnl_usd":-0.0059,"wilson_wr_lcb_pct":0.0,"wins":0,"wr_pct":0.0}],"wilson_wr_lcb_pct":25.8,"wins":7,"wr_pct":43.8},{"avg_mae_pct":null,"avg_mfe_pct":null,"engine":"INV_CONFLUENCE_BTC_WALL+SNIPER","losses":3,"mean_pnl_lcb_usd":-0.0251,"mean_pnl_usd":0.0144,"n":20,"recommended_keep":false,"sum_pnl_usd":0.2883,"top_coins":[{"avg_mae_pct":null,"avg_mfe_pct":null,"coin":"SNX","losses":0,"mean_pnl_lcb_usd":-0.0725,"mean_pnl_usd":0.1124,"n":4,"recommended_keep":false,"sum_pnl_usd":0.4496,"wilson_wr_lcb_pct":27.0,"wins":1,"wr_pct":100.0},{"avg_mae_pct":null,"avg_mfe_pct":null,"coin":"MOVE","losses":0,"mean_pnl_lcb_usd":0.0,"mean_pnl_usd":0.0,"n":4,"recommended_keep":false,"sum_pnl_usd":0.0,"wilson_wr_lcb_pct":0,"wins":0,"wr_pct":null},{"avg_mae_pct":null,"avg_mfe_pct":null,"coin":"SEI","losses":0,"mean_pnl_lcb_usd":0.0,"mean_pnl_usd":0.0,"n":2,"recommended_keep":false,"sum_pnl_usd":0.0,"wilson_wr_lcb_pct":0,"wins":0,"wr_pct":null},{"avg_mae_pct":null,"avg_mfe_pct":null,"coin":"SUSHI","losses":0,"mean_pnl_lcb_usd":0.0,"mean_pnl_usd":0.0,"n":2,"recommended_keep":false,"sum_pnl_usd":0.0,"wilson_wr_lcb_pct":0,"wins":0,"wr_pct":null},{"avg_mae_pct":null,"avg_mfe_pct":null,"coin":"ANIME","losses":0,"mean_pnl_lcb_usd":0.0,"mean_pnl_usd":0.0,"n":2,"recommended_keep":false,"sum_pnl_usd":0.0,"wilson_wr_lcb_pct":0,"wins":0,"wr_pct":null}],"wilson_wr_lcb_pct":14.3,"wins":2,"wr_pct":40.0},{"avg_mae_pct":-0.5707,"avg_mfe_pct":0.5702,"engine":"CONFLUENCE_NEWS+SNIPER","losses":10,"mean_pnl_lcb_usd":-0.0553,"mean_pnl_usd":-0.0258,"n":19,"recommended_keep":false,"sum_pnl_usd":-0.4911,"top_coins":[{"avg_mae_pct":-0.2355,"avg_mfe_pct":0.2331,"coin":"ASTER","losses":1,"mean_pnl_lcb_usd":-0.0003,"mean_pnl_usd":0.0001,"n":3,"recommended_keep":false,"sum_pnl_usd":0.0003,"wilson_wr_lcb_pct":12.1,"wins":1,"wr_pct":50.0},{"avg_mae_pct":-0.2001,"avg_mfe_pct":1.247,"coin":"SNX","losses":0,"mean_pnl_lcb_usd":-0.0006,"mean_pnl_usd":0.007,"n":3,"recommended_keep":false,"sum_pnl_usd":0.0209,"wilson_wr_lcb_pct":42.5,"wins":2,"wr_pct":100.0},{"avg_mae_pct":-0.9259,"avg_mfe_pct":0.5585,"coin":"ZK","losses":1,"mean_pnl_lcb_usd":-0.0046,"mean_pnl_usd":-0.0003,"n":2,"recommended_keep":false,"sum_pnl_usd":-0.0007,"wilson_wr_lcb_pct":12.1,"wins":1,"wr_pct":50.0},{"avg_mae_pct":-1.1866,"avg_mfe_pct":0.4215,"coin":"TAO","losses":1,"mean_pnl_lcb_usd":null,"mean_pnl_usd":-0.0027,"n":1,"recommended_keep":false,"sum_pnl_usd":-0.0027,"wilson_wr_lcb_pct":0.0,"wins":0,"wr_pct":0.0},{"avg_mae_pct":-0.2778,"avg_mfe_pct":0.2963,"coin":"ICP","losses":0,"mean_pnl_lcb_usd":null,"mean_pnl_usd":0.0001,"n":1,"recommended_keep":false,"sum_pnl_usd":0.0001,"wilson_wr_lcb_pct":27.0,"wins":1,"wr_pct":100.0}],"wilson_wr_lcb_pct":24.1,"wins":7,"wr_pct":41.2},{"avg_mae_pct":-0.4696,"avg_mfe_pct":0.204,"engine":"CONFLUENCE_DAY+NEWS","losses":7,"mean_pnl_lcb_usd":-0.0521,"mean_pnl_usd":0.0795,"n":19,"recommended_keep":false,"sum_pnl_usd":1.5105,"top_coins":[{"avg_mae_pct":-0.6168,"avg_mfe_pct":0.1712,"coin":"ZEN","losses":1,"mean_pnl_lcb_usd":-0.0015,"mean_pnl_usd":-0.0005,"n":4,"recommended_keep":false,"sum_pnl_usd":-0.0022,"wilson_wr_lcb_pct":0.0,"wins":0,"wr_pct":0.0},{"avg_mae_pct":-0.6431,"avg_mfe_pct":0.0,"coin":"HMSTR","losses":0,"mean_pnl_lcb_usd":0.0,"mean_pnl_usd":0.0,"n":2,"recommended_keep":false,"sum_pnl_usd":0.0,"wilson_wr_lcb_pct":0,"wins":0,"wr_pct":null},{"avg_mae_pct":-0.1102,"avg_mfe_pct":0.3089,"coin":"LINK","losses":1,"mean_pnl_lcb_usd":-0.0016,"mean_pnl_usd":-0.0002,"n":2,"recommended_keep":false,"sum_pnl_usd":-0.0004,"wilson_wr_lcb_pct":12.1,"wins":1,"wr_pct":50.0},{"avg_mae_pct":-0.7448,"avg_mfe_pct":0.4677,"coin":"TURBO","losses":0,"mean_pnl_lcb_usd":-0.0004,"mean_pnl_usd":0.0006,"n":2,"recommended_keep":false,"sum_pnl_usd":0.0012,"wilson_wr_lcb_pct":27.0,"wins":1,"wr_pct":100.0},{"avg_mae_pct":-0.2158,"avg_mfe_pct":0.2477,"coin":"XRP","losses":2,"mean_pnl_lcb_usd":-0.0037,"mean_pnl_usd":-0.0016,"n":2,"recommended_keep":false,"sum_pnl_usd":-0.0032,"wilson_wr_lcb_pct":0.0,"wins":0,"wr_pct":0.0}],"wilson_wr_lcb_pct":17.5,"wins":4,"wr_pct":36.4}],"err":null,"min_n":3,"target_wr_lcb_pct":55.00000000000001,"total_rows_window":644,"z":1.645}
,
  "edge_audit_bb_rej": {"by_close_reason":[{"avg_mae_pct":-1.2738,"avg_mfe_pct":0.6741,"close_reason":"exchange_fill","losses":1,"mean_pnl_lcb_usd":-0.1565,"mean_pnl_usd":-0.0132,"n":7,"recommended_keep":false,"sum_pnl_usd":-0.0924,"wilson_wr_lcb_pct":43.5,"wins":4,"wr_pct":80.0},{"avg_mae_pct":null,"avg_mfe_pct":null,"close_reason":"reconcile_phantom_clear","losses":0,"mean_pnl_lcb_usd":0.0,"mean_pnl_usd":0.0,"n":3,"recommended_keep":false,"sum_pnl_usd":0.0,"wilson_wr_lcb_pct":0,"wins":0,"wr_pct":null},{"avg_mae_pct":-1.0884,"avg_mfe_pct":3.8637,"close_reason":"profit_lock_2pct","losses":0,"mean_pnl_lcb_usd":-0.0682,"mean_pnl_usd":0.1483,"n":3,"recommended_keep":false,"sum_pnl_usd":0.4449,"wilson_wr_lcb_pct":52.6,"wins":3,"wr_pct":100.0}],"by_coin":[{"avg_mae_pct":-0.5584,"avg_mfe_pct":0.5161,"coin":"MINA","losses":0,"mean_pnl_lcb_usd":0.0,"mean_pnl_usd":0.0,"n":3,"recommended_keep":false,"sum_pnl_usd":0.0,"wilson_wr_lcb_pct":0,"wins":0,"wr_pct":null},{"avg_mae_pct":null,"avg_mfe_pct":null,"coin":"LAYER","losses":0,"mean_pnl_lcb_usd":null,"mean_pnl_usd":0.0017,"n":1,"recommended_keep":false,"sum_pnl_usd":0.0017,"wilson_wr_lcb_pct":27.0,"wins":1,"wr_pct":100.0},{"avg_mae_pct":null,"avg_mfe_pct":null,"coin":"ZRO","losses":0,"mean_pnl_lcb_usd":null,"mean_pnl_usd":0.0323,"n":1,"recommended_keep":false,"sum_pnl_usd":0.0323,"wilson_wr_lcb_pct":27.0,"wins":1,"wr_pct":100.0},{"avg_mae_pct":null,"avg_mfe_pct":null,"coin":"STX","losses":0,"mean_pnl_lcb_usd":null,"mean_pnl_usd":0.0,"n":1,"recommended_keep":false,"sum_pnl_usd":0.0,"wilson_wr_lcb_pct":0,"wins":0,"wr_pct":null},{"avg_mae_pct":-0.9706,"avg_mfe_pct":0.5711,"coin":"TRB","losses":0,"mean_pnl_lcb_usd":null,"mean_pnl_usd":0.0201,"n":1,"recommended_keep":false,"sum_pnl_usd":0.0201,"wilson_wr_lcb_pct":27.0,"wins":1,"wr_pct":100.0},{"avg_mae_pct":-3.9045,"avg_mfe_pct":0.0817,"coin":"SAND","losses":1,"mean_pnl_lcb_usd":null,"mean_pnl_usd":-0.4637,"n":1,"recommended_keep":false,"sum_pnl_usd":-0.4637,"wilson_wr_lcb_pct":0.0,"wins":0,"wr_pct":0.0},{"avg_mae_pct":-1.1816,"avg_mfe_pct":0.5916,"coin":"SEI","losses":0,"mean_pnl_lcb_usd":null,"mean_pnl_usd":0.0272,"n":1,"recommended_keep":false,"sum_pnl_usd":0.0272,"wilson_wr_lcb_pct":27.0,"wins":1,"wr_pct":100.0},{"avg_mae_pct":-1.0884,"avg_mfe_pct":3.8637,"coin":"APE","losses":0,"mean_pnl_lcb_usd":null,"mean_pnl_usd":0.4109,"n":1,"recommended_keep":false,"sum_pnl_usd":0.4109,"wilson_wr_lcb_pct":27.0,"wins":1,"wr_pct":100.0},{"avg_mae_pct":-0.4433,"avg_mfe_pct":0.5488,"coin":"LINK","losses":0,"mean_pnl_lcb_usd":null,"mean_pnl_usd":0.0017,"n":1,"recommended_keep":false,"sum_pnl_usd":0.0017,"wilson_wr_lcb_pct":27.0,"wins":1,"wr_pct":100.0},{"avg_mae_pct":-0.5846,"avg_mfe_pct":1.7353,"coin":"SNX","losses":0,"mean_pnl_lcb_usd":null,"mean_pnl_usd":0.3223,"n":1,"recommended_keep":false,"sum_pnl_usd":0.3223,"wilson_wr_lcb_pct":27.0,"wins":1,"wr_pct":100.0},{"avg_mae_pct":null,"avg_mfe_pct":null,"coin":"LINEA","losses":0,"mean_pnl_lcb_usd":null,"mean_pnl_usd":0.0,"n":1,"recommended_keep":false,"sum_pnl_usd":0.0,"wilson_wr_lcb_pct":0,"wins":0,"wr_pct":null}],"by_hour_utc":[{"avg_mae_pct":-0.5846,"avg_mfe_pct":1.7353,"hour_utc":5,"losses":0,"mean_pnl_lcb_usd":-0.1039,"mean_pnl_usd":0.1611,"n":2,"recommended_keep":false,"sum_pnl_usd":0.3223,"wilson_wr_lcb_pct":27.0,"wins":1,"wr_pct":100.0},{"avg_mae_pct":-0.5584,"avg_mfe_pct":0.5161,"hour_utc":6,"losses":0,"mean_pnl_lcb_usd":0.0,"mean_pnl_usd":0.0,"n":2,"recommended_keep":false,"sum_pnl_usd":0.0,"wilson_wr_lcb_pct":0,"wins":0,"wr_pct":null},{"avg_mae_pct":null,"avg_mfe_pct":null,"hour_utc":8,"losses":0,"mean_pnl_lcb_usd":-0.0059,"mean_pnl_usd":0.0113,"n":3,"recommended_keep":false,"sum_pnl_usd":0.034,"wilson_wr_lcb_pct":42.5,"wins":2,"wr_pct":100.0},{"avg_mae_pct":null,"avg_mfe_pct":null,"hour_utc":13,"losses":0,"mean_pnl_lcb_usd":null,"mean_pnl_usd":0.0,"n":1,"recommended_keep":false,"sum_pnl_usd":0.0,"wilson_wr_lcb_pct":0,"wins":0,"wr_pct":null},{"avg_mae_pct":-0.9706,"avg_mfe_pct":0.5711,"hour_utc":14,"losses":0,"mean_pnl_lcb_usd":null,"mean_pnl_usd":0.0201,"n":1,"recommended_keep":false,"sum_pnl_usd":0.0201,"wilson_wr_lcb_pct":27.0,"wins":1,"wr_pct":100.0},{"avg_mae_pct":-3.9045,"avg_mfe_pct":0.0817,"hour_utc":16,"losses":1,"mean_pnl_lcb_usd":null,"mean_pnl_usd":-0.4637,"n":1,"recommended_keep":false,"sum_pnl_usd":-0.4637,"wilson_wr_lcb_pct":0.0,"wins":0,"wr_pct":0.0},{"avg_mae_pct":-1.1816,"avg_mfe_pct":0.5916,"hour_utc":17,"losses":0,"mean_pnl_lcb_usd":null,"mean_pnl_usd":0.0272,"n":1,"recommended_keep":false,"sum_pnl_usd":0.0272,"wilson_wr_lcb_pct":27.0,"wins":1,"wr_pct":100.0},{"avg_mae_pct":-1.0884,"avg_mfe_pct":3.8637,"hour_utc":20,"losses":0,"mean_pnl_lcb_usd":null,"mean_pnl_usd":0.4109,"n":1,"recommended_keep":false,"sum_pnl_usd":0.4109,"wilson_wr_lcb_pct":27.0,"wins":1,"wr_pct":100.0},{"avg_mae_pct":-0.4433,"avg_mfe_pct":0.5488,"hour_utc":21,"losses":0,"mean_pnl_lcb_usd":null,"mean_pnl_usd":0.0017,"n":1,"recommended_keep":false,"sum_pnl_usd":0.0017,"wilson_wr_lcb_pct":27.0,"wins":1,"wr_pct":100.0}],"by_regime":[{"avg_mae_pct":-2.4375,"avg_mfe_pct":0.3264,"losses":1,"mean_pnl_lcb_usd":-0.1699,"mean_pnl_usd":-0.0585,"n":7,"recommended_keep":false,"regime":"unknown","sum_pnl_usd":-0.4096,"wilson_wr_lcb_pct":35.6,"wins":3,"wr_pct":75.0},{"avg_mae_pct":-0.9044,"avg_mfe_pct":1.668,"losses":0,"mean_pnl_lcb_usd":-0.0711,"mean_pnl_usd":0.1466,"n":3,"recommended_keep":false,"regime":"chop","sum_pnl_usd":0.4398,"wilson_wr_lcb_pct":52.6,"wins":3,"wr_pct":100.0},{"avg_mae_pct":-0.5715,"avg_mfe_pct":1.1257,"losses":0,"mean_pnl_lcb_usd":-0.0693,"mean_pnl_usd":0.1074,"n":3,"recommended_keep":false,"regime":"bear-calm","sum_pnl_usd":0.3223,"wilson_wr_lcb_pct":27.0,"wins":1,"wr_pct":100.0}],"by_side":[{"avg_mae_pct":-1.2738,"avg_mfe_pct":0.6741,"losses":1,"mean_pnl_lcb_usd":-0.0969,"mean_pnl_usd":-0.0082,"n":11,"recommended_keep":false,"side":"SELL","sum_pnl_usd":-0.0907,"wilson_wr_lcb_pct":49.8,"wins":5,"wr_pct":83.3},{"avg_mae_pct":-1.0884,"avg_mfe_pct":3.8637,"losses":0,"mean_pnl_lcb_usd":-0.0898,"mean_pnl_usd":0.2216,"n":2,"recommended_keep":false,"side":"BUY","sum_pnl_usd":0.4432,"wilson_wr_lcb_pct":42.5,"wins":2,"wr_pct":100.0}],"days":14,"discouraged_coins_with_data":["MINA"],"engine":"BB_REJ","err":null,"mfe_distribution":{">=100bp":{"n":2,"pct":15.4},">=10bp":{"n":6,"pct":46.2},">=20bp":{"n":6,"pct":46.2},">=30bp":{"n":6,"pct":46.2},">=50bp":{"n":6,"pct":46.2},">=5bp":{"n":7,"pct":53.8}},"min_n":3,"overall":{"avg_mae_pct":-1.2473,"avg_mfe_pct":1.1298,"engine":"BB_REJ","losses":1,"mean_pnl_lcb_usd":-0.0642,"mean_pnl_usd":0.0271,"n":13,"recommended_keep":false,"sum_pnl_usd":0.3525,"wilson_wr_lcb_pct":58.9,"wins":7,"wr_pct":87.5},"recommended_coin_allowlist":[],"sample_recent_trades":[{"close_reason":"reconcile_phantom_clear","coin":"LINEA","engine":"BB_REJ","hour_utc":6,"iso":"2026-04-27T06:48:13+00:00","mae_pct":null,"mfe_pct":null,"pnl":0.0,"regime":"bear-calm","side":"SELL","ts":1777272493},{"close_reason":"exchange_fill","coin":"MINA","engine":"BB_REJ","hour_utc":6,"iso":"2026-04-27T06:15:53+00:00","mae_pct":-0.005584401323942261,"mfe_pct":0.005160865268474736,"pnl":0.0,"regime":"bear-calm","side":"SELL","ts":1777270553},{"close_reason":"exchange_fill","coin":"SNX","engine":"BB_REJ","hour_utc":5,"iso":"2026-04-27T05:44:47+00:00","mae_pct":-0.00584632516703787,"mfe_pct":0.01735337787676319,"pnl":0.3223,"regime":"bear-calm","side":"SELL","ts":1777268687},{"close_reason":"exchange_fill","coin":"LINK","engine":"BB_REJ","hour_utc":21,"iso":"2026-04-26T21:55:21+00:00","mae_pct":-0.0044327176781002444,"mfe_pct":0.005488126649076475,"pnl":0.0017,"regime":"chop","side":"SELL","ts":1777240521},{"close_reason":"profit_lock_2pct","coin":"APE","engine":"BB_REJ","hour_utc":20,"iso":"2026-04-26T20:31:39+00:00","mae_pct":-0.010883613359635332,"mfe_pct":0.0386368274267056,"pnl":0.4109,"regime":"chop","side":"BUY","ts":1777235499},{"close_reason":"exchange_fill","coin":"SEI","engine":"BB_REJ","hour_utc":17,"iso":"2026-04-26T17:29:28+00:00","mae_pct":-0.011816398587681283,"mfe_pct":0.005916045508042406,"pnl":0.0272,"regime":"chop","side":"SELL","ts":1777224568},{"close_reason":"exchange_fill","coin":"SAND","engine":"BB_REJ","hour_utc":16,"iso":"2026-04-26T16:30:40+00:00","mae_pct":-0.03904462602137018,"mfe_pct":0.0008170961659333202,"pnl":-0.4637,"regime":"","side":"SELL","ts":1777221040},{"close_reason":"exchange_fill","coin":"TRB","engine":"BB_REJ","hour_utc":14,"iso":"2026-04-26T14:19:43+00:00","mae_pct":-0.009706134706134757,"mfe_pct":0.005711068211068237,"pnl":0.0201,"regime":"","side":"SELL","ts":1777213183},{"close_reason":"reconcile_phantom_clear","coin":"STX","engine":"BB_REJ","hour_utc":13,"iso":"2026-04-26T13:34:29+00:00","mae_pct":null,"mfe_pct":null,"pnl":0.0,"regime":"","side":"SELL","ts":1777210469},{"close_reason":"profit_lock_2pct","coin":"ZRO","engine":"BB_REJ","hour_utc":8,"iso":"2026-04-26T08:55:45+00:00","mae_pct":null,"mfe_pct":null,"pnl":0.0323,"regime":"","side":"BUY","ts":1777193745}],"target_wr_lcb_pct":55.00000000000001,"total_rows_engine":13,"z":1.645}
,
  "edge_audit_liq_cscd": {"days":14,"engine":"LIQ_CSCD","err":null,"note":"no closed trades for LIQ_CSCD in lookback"}
,
  "hour_veto_status": {"audit_baseline_per_hour":{"4":{"n":22,"sum_pnl":-1.06},"6":{"n":18,"sum_pnl":-0.78},"7":{"n":25,"sum_pnl":-2.79},"9":{"n":24,"sum_pnl":-2.03},"14":{"n":21,"sum_pnl":-1.54},"15":{"n":23,"sum_pnl":-2.26},"16":{"n":19,"sum_pnl":-0.83},"19":{"n":27,"sum_pnl":-2.26}},"blocked_hours_utc":[4,6,7,9,14,15,16,19],"calibration_note":"Wilson CIs wide on n<30 buckets. Re-run /analyze by_hour_utc at +100 closes to confirm. Use HOUR_VETO_HOURS env to tune.","current_hour_utc":14,"currently_blocking":false,"enabled":false,"reason":"disabled","stats":{"blocks":0,"blocks_per_hour":{},"checks":4}}
,
  "bad_entry_kill_status": {"already_killed_this_session":[],"config":{"age_sec":60,"enabled":true,"max_age_sec":90,"min_mfe_pct":0.05},"live_kill_candidates_now":[],"positions_total":1,"skipped_beyond_window":0,"skipped_has_mfe":0,"skipped_too_young":0}
,
  "bucket_filter_status": {"block_invocations_per_bucket":{},"blocked_buckets":4,"cache_ttl_s":3600,"enabled":true,"last_refresh_age_sec":1233,"last_refresh_err":null,"last_refresh_ts":1777643193,"mfe_pos_threshold_pct":0.5,"mfe_rate_floor_pct":40.0,"min_samples":3,"refresh_count":4,"top_blocked":[{"blocked":true,"coin":"W","engine":"CONFLUENCE_BTC_WALL+SNIPER","mfe_pos":0,"mfe_pos_rate_pct":0.0,"n":3,"regime":"bear-calm"},{"blocked":true,"coin":"ANIME","engine":"CONFLUENCE_BTC_WALL+NEWS","mfe_pos":1,"mfe_pos_rate_pct":33.3,"n":3,"regime":"bear-calm"},{"blocked":true,"coin":"OP","engine":"CONFLUENCE_BTC_WALL+OBI","mfe_pos":1,"mfe_pos_rate_pct":33.3,"n":3,"regime":"chop"},{"blocked":true,"coin":"LTC","engine":"CONFLUENCE_BTC_WALL+DAY+SNIPER","mfe_pos":0,"mfe_pos_rate_pct":0.0,"n":3,"regime":"bear-calm"}],"top_buckets_by_sample":[{"blocked":true,"coin":"W","engine":"CONFLUENCE_BTC_WALL+SNIPER","mfe_pos":0,"mfe_pos_rate_pct":0.0,"n":3,"regime":"bear-calm"},{"blocked":true,"coin":"ANIME","engine":"CONFLUENCE_BTC_WALL+NEWS","mfe_pos":1,"mfe_pos_rate_pct":33.3,"n":3,"regime":"bear-calm"},{"blocked":true,"coin":"OP","engine":"CONFLUENCE_BTC_WALL+OBI","mfe_pos":1,"mfe_pos_rate_pct":33.3,"n":3,"regime":"chop"},{"blocked":true,"coin":"LTC","engine":"CONFLUENCE_BTC_WALL+DAY+SNIPER","mfe_pos":0,"mfe_pos_rate_pct":0.0,"n":3,"regime":"bear-calm"},{"blocked":false,"coin":"BLAST","engine":"FUNDING_MR","mfe_pos":2,"mfe_pos_rate_pct":66.7,"n":3,"regime":"chop"},{"blocked":false,"coin":"APE","engine":"CONFLUENCE_BTC_WALL+DAY","mfe_pos":2,"mfe_pos_rate_pct":66.7,"n":3,"regime":"bear-calm"},{"blocked":false,"coin":"POL","engine":"FUNDING_MR","mfe_pos":2,"mfe_pos_rate_pct":100.0,"n":2,"regime":"chop"},{"blocked":false,"coin":"GRASS","engine":"PIVOT","mfe_pos":2,"mfe_pos_rate_pct":100.0,"n":2,"regime":"chop"},{"blocked":false,"coin":"RSR","engine":"PIVOT","mfe_pos":2,"mfe_pos_rate_pct":100.0,"n":2,"regime":"chop"},{"blocked":false,"coin":"AAVE","engine":"WALL_BNC","mfe_pos":1,"mfe_pos_rate_pct":50.0,"n":2,"regime":"bull-calm"},{"blocked":false,"coin":"S","engine":"CONFLUENCE_BTC_WALL+SNIPER","mfe_pos":0,"mfe_pos_rate_pct":0.0,"n":2,"regime":"bear-calm"},{"blocked":false,"coin":"GRASS","engine":"CONFLUENCE_BTC_WALL+SNIPER","mfe_pos":1,"mfe_pos_rate_pct":50.0,"n":2,"regime":"bear-calm"},{"blocked":false,"coin":"TURBO","engine":"CONFLUENCE_BTC_WALL+SNIPER","mfe_pos":1,"mfe_pos_rate_pct":50.0,"n":2,"regime":"bear-calm"},{"blocked":false,"coin":"APE","engine":"CONFLUENCE_BTC_WALL+OBI","mfe_pos":0,"mfe_pos_rate_pct":0.0,"n":2,"regime":"chop"},{"blocked":false,"coin":"NOT","engine":"CONFLUENCE_BTC_WALL+OBI","mfe_pos":2,"mfe_pos_rate_pct":100.0,"n":2,"regime":"chop"},{"blocked":false,"coin":"BNB","engine":"CONFLUENCE_BTC_WALL+DAY","mfe_pos":0,"mfe_pos_rate_pct":0.0,"n":2,"regime":"bear-calm"},{"blocked":false,"coin":"ORDI","engine":"CONFLUENCE_BTC_WALL+SNIPER","mfe_pos":2,"mfe_pos_rate_pct":100.0,"n":2,"regime":"chop"},{"blocked":false,"coin":"INJ","engine":"CONFLUENCE_BTC_WALL+OBI","mfe_pos":1,"mfe_pos_rate_pct":50.0,"n":2,"regime":"chop"},{"blocked":false,"coin":"AAVE","engine":"CONFLUENCE_BTC_WALL+OBI","mfe_pos":1,"mfe_pos_rate_pct":50.0,"n":2,"regime":"chop"},{"blocked":false,"coin":"MERL","engine":"CONFLUENCE_BTC_WALL+SNIPER","mfe_pos":2,"mfe_pos_rate_pct":100.0,"n":2,"regime":"chop"},{"blocked":false,"coin":"S","engine":"CONFLUENCE_BTC_WALL+SNIPER","mfe_pos":0,"mfe_pos_rate_pct":0.0,"n":2,"regime":"chop"},{"blocked":false,"coin":"SNX","engine":"CONFLUENCE_NEWS+SNIPER","mfe_pos":2,"mfe_pos_rate_pct":100.0,"n":2,"regime":"chop"},{"blocked":false,"coin":"LDO","engine":"CONFLUENCE_BTC_WALL+OBI","mfe_pos":1,"mfe_pos_rate_pct":50.0,"n":2,"regime":"chop"},{"blocked":false,"coin":"CC","engine":"CONFLUENCE_BTC_WALL+DAY+SNIPER","mfe_pos":2,"mfe_pos_rate_pct":100.0,"n":2,"regime":"chop"},{"blocked":false,"coin":"TURBO","engine":"CONFLUENCE_BTC_WALL+SNIPER","mfe_pos":0,"mfe_pos_rate_pct":0.0,"n":2,"regime":"chop"}],"total_buckets":279}
,
  "trades_recent": {"breakeven":76,"by_coin":{"AAVE":{"avg_mae_pct":-0.204,"avg_mfe_pct":0.31,"b":0,"l":1,"n":1,"pnl":-0.0017,"w":0,"wr":0.0},"ANIME":{"avg_mae_pct":null,"avg_mfe_pct":null,"b":5,"l":0,"n":5,"pnl":0.0,"w":0,"wr":null},"APE":{"avg_mae_pct":null,"avg_mfe_pct":null,"b":0,"l":0,"n":1,"pnl":0.0001,"w":1,"wr":100.0},"ETC":{"avg_mae_pct":-0.297,"avg_mfe_pct":0.033,"b":0,"l":0,"n":1,"pnl":0.0001,"w":1,"wr":100.0},"ICP":{"avg_mae_pct":-0.524,"avg_mfe_pct":0.225,"b":3,"l":1,"n":4,"pnl":-0.0052,"w":0,"wr":0.0},"INJ":{"avg_mae_pct":-0.066,"avg_mfe_pct":0.832,"b":0,"l":0,"n":2,"pnl":0.0966,"w":2,"wr":100.0},"IP":{"avg_mae_pct":null,"avg_mfe_pct":null,"b":3,"l":0,"n":3,"pnl":0.0,"w":0,"wr":null},"JUP":{"avg_mae_pct":0.0,"avg_mfe_pct":1.603,"b":3,"l":0,"n":4,"pnl":0.6808,"w":1,"wr":100.0},"LAYER":{"avg_mae_pct":null,"avg_mfe_pct":null,"b":3,"l":0,"n":3,"pnl":0.0,"w":0,"wr":null},"LTC":{"avg_mae_pct":null,"avg_mfe_pct":null,"b":3,"l":0,"n":3,"pnl":0.0,"w":0,"wr":null},"MERL":{"avg_mae_pct":0.0,"avg_mfe_pct":2.023,"b":9,"l":1,"n":11,"pnl":0.457,"w":1,"wr":50.0},"MEW":{"avg_mae_pct":0.0,"avg_mfe_pct":0.895,"b":1,"l":0,"n":1,"pnl":0.0,"w":0,"wr":null},"MOVE":{"avg_mae_pct":null,"avg_mfe_pct":null,"b":4,"l":0,"n":4,"pnl":0.0,"w":0,"wr":null},"NEAR":{"avg_mae_pct":null,"avg_mfe_pct":null,"b":0,"l":1,"n":1,"pnl":-0.2227,"w":0,"wr":0.0},"NEO":{"avg_mae_pct":null,"avg_mfe_pct":null,"b":3,"l":0,"n":3,"pnl":0.0,"w":0,"wr":null},"NOT":{"avg_mae_pct":0.0,"avg_mfe_pct":0.542,"b":0,"l":0,"n":1,"pnl":0.0028,"w":1,"wr":100.0},"OP":{"avg_mae_pct":null,"avg_mfe_pct":null,"b":0,"l":0,"n":1,"pnl":0.0001,"w":1,"wr":100.0},"ORDI":{"avg_mae_pct":0.0,"avg_mfe_pct":1.004,"b":0,"l":0,"n":1,"pnl":0.1297,"w":1,"wr":100.0},"PROVE":{"avg_mae_pct":null,"avg_mfe_pct":null,"b":0,"l":1,"n":1,"pnl":-0.0003,"w":0,"wr":0.0},"PUMP":{"avg_mae_pct":null,"avg_mfe_pct":null,"b":2,"l":0,"n":2,"pnl":0.0,"w":0,"wr":null},"SAND":{"avg_mae_pct":0.0,"avg_mfe_pct":1.067,"b":0,"l":0,"n":1,"pnl":0.0008,"w":1,"wr":100.0},"SEI":{"avg_mae_pct":-0.871,"avg_mfe_pct":0.0,"b":6,"l":2,"n":8,"pnl":-0.0174,"w":0,"wr":0.0},"SNX":{"avg_mae_pct":null,"avg_mfe_pct":null,"b":3,"l":0,"n":4,"pnl":0.4496,"w":1,"wr":100.0},"SOL":{"avg_mae_pct":-0.533,"avg_mfe_pct":0.134,"b":2,"l":1,"n":3,"pnl":-0.0053,"w":0,"wr":0.0},"STABLE":{"avg_mae_pct":null,"avg_mfe_pct":null,"b":5,"l":0,"n":5,"pnl":0.0,"w":0,"wr":null},"SUSHI":{"avg_mae_pct":null,"avg_mfe_pct":null,"b":2,"l":0,"n":2,"pnl":0.0,"w":0,"wr":null},"TAO":{"avg_mae_pct":null,"avg_mfe_pct":null,"b":4,"l":0,"n":5,"pnl":1.914,"w":1,"wr":100.0},"TURBO":{"avg_mae_pct":-0.534,"avg_mfe_pct":0.0,"b":0,"l":1,"n":1,"pnl":-0.0053,"w":0,"wr":0.0},"UMA":{"avg_mae_pct":null,"avg_mfe_pct":null,"b":1,"l":0,"n":1,"pnl":0.0,"w":0,"wr":null},"W":{"avg_mae_pct":null,"avg_mfe_pct":null,"b":4,"l":0,"n":4,"pnl":0.0,"w":0,"wr":null},"WIF":{"avg_mae_pct":null,"avg_mfe_pct":null,"b":3,"l":0,"n":3,"pnl":0.0,"w":0,"wr":null},"WLFI":{"avg_mae_pct":-4.655,"avg_mfe_pct":0.0,"b":0,"l":1,"n":1,"pnl":-0.0466,"w":0,"wr":0.0},"XRP":{"avg_mae_pct":null,"avg_mfe_pct":null,"b":4,"l":0,"n":4,"pnl":0.0,"w":0,"wr":null},"ZEN":{"avg_mae_pct":null,"avg_mfe_pct":null,"b":3,"l":0,"n":3,"pnl":0.0,"w":0,"wr":null}},"by_engine":{"CONFLUENCE_BTC_WALL+CVD+DAY":{"_is_noise":false,"avg_mae_pct":-0.533,"avg_mfe_pct":0.134,"b":0,"l":1,"n":1,"pnl":-0.0053,"w":0,"wr":0.0},"CONFLUENCE_BTC_WALL+OBI":{"_is_noise":false,"avg_mae_pct":0.0,"avg_mfe_pct":1.222,"b":3,"l":1,"n":7,"pnl":-0.1266,"w":3,"wr":75.0},"CONFLUENCE_BTC_WALL+OBI+SNIPER":{"_is_noise":false,"avg_mae_pct":0.0,"avg_mfe_pct":0.805,"b":0,"l":0,"n":2,"pnl":0.0036,"w":2,"wr":100.0},"CONFLUENCE_DAY+FUNDING+SNIPER":{"_is_noise":false,"avg_mae_pct":-0.524,"avg_mfe_pct":0.225,"b":0,"l":1,"n":1,"pnl":-0.0052,"w":0,"wr":0.0},"CONFLUENCE_DAY+NEWS":{"_is_noise":false,"avg_mae_pct":null,"avg_mfe_pct":null,"b":3,"l":0,"n":3,"pnl":0.0,"w":0,"wr":null},"CONFLUENCE_DAY+NEWS+SNIPER":{"_is_noise":false,"avg_mae_pct":null,"avg_mfe_pct":null,"b":6,"l":0,"n":6,"pnl":0.0,"w":0,"wr":null},"CONFLUENCE_FUNDING+NEWS":{"_is_noise":false,"avg_mae_pct":-4.655,"avg_mfe_pct":0.0,"b":3,"l":1,"n":4,"pnl":-0.0466,"w":0,"wr":0.0},"CONFLUENCE_FUNDING+NEWS+SNIPER":{"_is_noise":false,"avg_mae_pct":null,"avg_mfe_pct":null,"b":3,"l":0,"n":3,"pnl":0.0,"w":0,"wr":null},"CONFLUENCE_FUNDING+OBI":{"_is_noise":false,"avg_mae_pct":0.0,"avg_mfe_pct":0.895,"b":1,"l":0,"n":1,"pnl":0.0,"w":0,"wr":null},"CONFLUENCE_FUNDING+SNIPER":{"_is_noise":false,"avg_mae_pct":0.0,"avg_mfe_pct":2.023,"b":6,"l":1,"n":8,"pnl":0.457,"w":1,"wr":50.0},"CONFLUENCE_OBI+OI":{"_is_noise":false,"avg_mae_pct":-0.132,"avg_mfe_pct":0.443,"b":0,"l":0,"n":1,"pnl":0.0007,"w":1,"wr":100.0},"CONFLUENCE_OBI+SNIPER":{"_is_noise":false,"avg_mae_pct":-0.068,"avg_mfe_pct":0.972,"b":0,"l":1,"n":3,"pnl":0.8088,"w":2,"wr":66.7},"INV_CONFLUENCE_BTC_WALL+DAY":{"_is_noise":false,"avg_mae_pct":null,"avg_mfe_pct":null,"b":16,"l":0,"n":17,"pnl":1.914,"w":1,"wr":100.0},"INV_CONFLUENCE_BTC_WALL+DAY+SNIPER":{"_is_noise":false,"avg_mae_pct":-0.758,"avg_mfe_pct":0.0,"b":15,"l":3,"n":18,"pnl":-0.0227,"w":0,"wr":0.0},"INV_CONFLUENCE_BTC_WALL+SNIPER":{"_is_noise":false,"avg_mae_pct":null,"avg_mfe_pct":null,"b":14,"l":1,"n":16,"pnl":0.4493,"w":1,"wr":50.0},"INV_CONFLUENCE_NEWS+SNIPER":{"_is_noise":false,"avg_mae_pct":-0.297,"avg_mfe_pct":0.033,"b":6,"l":0,"n":7,"pnl":0.0001,"w":1,"wr":100.0}},"by_hour":{"2026-05-01T02":{"avg_mae_pct":-0.174,"avg_mfe_pct":0.677,"b":1,"l":2,"n":5,"pnl":0.6745,"w":2,"wr":50.0},"2026-05-01T03":{"avg_mae_pct":-0.534,"avg_mfe_pct":0.0,"b":0,"l":3,"n":4,"pnl":-0.2282,"w":1,"wr":25.0},"2026-05-01T04":{"avg_mae_pct":0.0,"avg_mfe_pct":1.004,"b":0,"l":0,"n":1,"pnl":0.1297,"w":1,"wr":100.0},"2026-05-01T05":{"avg_mae_pct":0.0,"avg_mfe_pct":0.805,"b":0,"l":0,"n":3,"pnl":0.0037,"w":3,"wr":100.0},"2026-05-01T07":{"avg_mae_pct":-0.148,"avg_mfe_pct":0.628,"b":0,"l":0,"n":3,"pnl":0.5456,"w":3,"wr":100.0},"2026-05-01T08":{"avg_mae_pct":null,"avg_mfe_pct":null,"b":0,"l":1,"n":1,"pnl":-0.2555,"w":0,"wr":0.0},"2026-05-01T09":{"avg_mae_pct":-2.01,"avg_mfe_pct":0.075,"b":16,"l":3,"n":19,"pnl":-0.0603,"w":0,"wr":0.0},"2026-05-01T10":{"avg_mae_pct":-0.89,"avg_mfe_pct":0.0,"b":59,"l":1,"n":61,"pnl":1.9051,"w":1,"wr":50.0},"2026-05-01T12":{"avg_mae_pct":0.0,"avg_mfe_pct":2.023,"b":0,"l":0,"n":1,"pnl":0.7125,"w":1,"wr":100.0}},"by_side":{"BUY":{"avg_mae_pct":-0.708,"avg_mfe_pct":0.591,"b":67,"l":8,"n":81,"pnl":3.5553,"w":6,"wr":42.9},"SELL":{"avg_mae_pct":-0.166,"avg_mfe_pct":0.6,"b":9,"l":2,"n":17,"pnl":-0.1282,"w":6,"wr":75.0}},"closed_with_pnl":98,"cutoff_utc":"2026-05-01T02:07:07.441985+00:00","last_20":[{"_pnl_f":null,"_ts":"2026-05-01T10:34:15+00:00","cloid":"c86d5539SUSHL","close_reason":"","coin":"SUSHI","direction":"BUY","engine":"INV_CONFLUENCE_BTC_WALL+SNIPER","entry":"0.209","entry_price":"0.209","event_seq":"2459","event_type":"ENTRY","exchange_fill_id":"","exit_price":"","expected_edge_at_entry":"0.0136","funding_paid_pct":"","mae_pct":"","mfe_pct":"","pnl":"","realized_slippage_pct":"","regime":"bull-calm","side":"BUY","sl_pct":"0.005","source":"confluence_signal","timestamp":"2026-05-01T10:34:15+00:00","tp_pct":"0.015","trade_id":"c86d5539d260"},{"_pnl_f":0.0,"_ts":"2026-05-01T10:34:29+00:00","cloid":"c86d5539SUSHL","close_reason":"confluence_no_fill","coin":"SUSHI","direction":"CLOSE","engine":"INV_CONFLUENCE_BTC_WALL+SNIPER","entry":"","entry_price":"0.209","event_seq":"2460","event_type":"CLOSE","exchange_fill_id":"","exit_price":"","expected_edge_at_entry":"0.0136","funding_paid_pct":"","mae_pct":"","mfe_pct":"","pnl":"0","realized_slippage_pct":"","regime":"bull-calm","side":"BUY","sl_pct":"0.005","source":"confluence_close","timestamp":"2026-05-01T10:34:29+00:00","tp_pct":"0.015","trade_id":"c86d5539d260"},{"_pnl_f":null,"_ts":"2026-05-01T10:34:29+00:00","cloid":"6ece72ccANIML","close_reason":"","coin":"ANIME","direction":"BUY","engine":"INV_CONFLUENCE_BTC_WALL+SNIPER","entry":"0.004694","entry_price":"0.004694","event_seq":"2461","event_type":"ENTRY","exchange_fill_id":"","exit_price":"","expected_edge_at_entry":"0.0136","funding_paid_pct":"","mae_pct":"","mfe_pct":"","pnl":"","realized_slippage_pct":"","regime":"bull-calm","side":"BUY","sl_pct":"0.005","source":"confluence_signal","timestamp":"2026-05-01T10:34:29+00:00","tp_pct":"0.015","trade_id":"6ece72cc7720"},{"_pnl_f":0.0,"_ts":"2026-05-01T10:34:43+00:00","cloid":"6ece72ccANIML","close_reason":"confluence_no_fill","coin":"ANIME","direction":"CLOSE","engine":"INV_CONFLUENCE_BTC_WALL+SNIPER","entry":"","entry_price":"0.004694","event_seq":"2462","event_type":"CLOSE","exchange_fill_id":"","exit_price":"","expected_edge_at_entry":"0.0136","funding_paid_pct":"","mae_pct":"","mfe_pct":"","pnl":"0","realized_slippage_pct":"","regime":"bull-calm","side":"BUY","sl_pct":"0.005","source":"confluence_close","timestamp":"2026-05-01T10:34:43+00:00","tp_pct":"0.015","trade_id":"6ece72cc7720"},{"_pnl_f":null,"_ts":"2026-05-01T10:34:43+00:00","cloid":"f2d40319MERLL","close_reason":"","coin":"MERL","direction":"BUY","engine":"CONFLUENCE_FUNDING+SNIPER","entry":"0.03226","entry_price":"0.03226","event_seq":"2463","event_type":"ENTRY","exchange_fill_id":"","exit_price":"","expected_edge_at_entry":"0.0136","funding_paid_pct":"","mae_pct":"","mfe_pct":"","pnl":"","realized_slippage_pct":"","regime":"bull-calm","side":"BUY","sl_pct":"0.005","source":"confluence_signal","timestamp":"2026-05-01T10:34:43+00:00","tp_pct":"0.015","trade_id":"f2d4031998b2"},{"_pnl_f":0.0,"_ts":"2026-05-01T10:34:56+00:00","cloid":"f2d40319MERLL","close_reason":"confluence_no_fill","coin":"MERL","direction":"CLOSE","engine":"CONFLUENCE_FUNDING+SNIPER","entry":"","entry_price":"0.03226","event_seq":"2464","event_type":"CLOSE","exchange_fill_id":"","exit_price":"","expected_edge_at_entry":"0.0136","funding_paid_pct":"","mae_pct":"","mfe_pct":"","pnl":"0","realized_slippage_pct":"","regime":"bull-calm","side":"BUY","sl_pct":"0.005","source":"confluence_close","timestamp":"2026-05-01T10:34:56+00:00","tp_pct":"0.015","trade_id":"f2d4031998b2"},{"_pnl_f":null,"_ts":"2026-05-01T10:34:56+00:00","cloid":"d24a8b12MOVEL","close_reason":"","coin":"MOVE","direction":"BUY","engine":"INV_CONFLUENCE_BTC_WALL+SNIPER","entry":"0.01745","entry_price":"0.01745","event_seq":"2465","event_type":"ENTRY","exchange_fill_id":"","exit_price":"","expected_edge_at_entry":"0.0136","funding_paid_pct":"","mae_pct":"","mfe_pct":"","pnl":"","realized_slippage_pct":"","regime":"bull-calm","side":"BUY","sl_pct":"0.005","source":"confluence_signal","timestamp":"2026-05-01T10:34:56+00:00","tp_pct":"0.015","trade_id":"d24a8b123f24"},{"_pnl_f":0.0,"_ts":"2026-05-01T10:35:10+00:00","cloid":"d24a8b12MOVEL","close_reason":"confluence_no_fill","coin":"MOVE","direction":"CLOSE","engine":"INV_CONFLUENCE_BTC_WALL+SNIPER","entry":"","entry_price":"0.01745","event_seq":"2466","event_type":"CLOSE","exchange_fill_id":"","exit_price":"","expected_edge_at_entry":"0.0136","funding_paid_pct":"","mae_pct":"","mfe_pct":"","pnl":"0","realized_slippage_pct":"","regime":"bull-calm","side":"BUY","sl_pct":"0.005","source":"confluence_close","timestamp":"2026-05-01T10:35:10+00:00","tp_pct":"0.015","trade_id":"d24a8b123f24"},{"_pnl_f":null,"_ts":"2026-05-01T10:35:10+00:00","cloid":"d3598584NEOL","close_reason":"","coin":"NEO","direction":"BUY","engine":"INV_CONFLUENCE_BTC_WALL+SNIPER","entry":"2.713","entry_price":"2.713","event_seq":"2467","event_type":"ENTRY","exchange_fill_id":"","exit_price":"","expected_edge_at_entry":"0.0136","funding_paid_pct":"","mae_pct":"","mfe_pct":"","pnl":"","realized_slippage_pct":"","regime":"bull-calm","side":"BUY","sl_pct":"0.005","source":"confluence_signal","timestamp":"2026-05-01T10:35:10+00:00","tp_pct":"0.015","trade_id":"d3598584c518"},{"_pnl_f":null,"_ts":"2026-05-01T10:35:44+00:00","cloid":"4eaae837MERLL","close_reason":"","coin":"MERL","direction":"BUY","engine":"CONFLUENCE_FUNDING+SNIPER","entry":"0.03224","entry_price":"0.03224","event_seq":"2468","event_type":"ENTRY","exchange_fill_id":"","exit_price":"","expected_edge_at_entry":"0.018600000000000002","funding_paid_pct":"","mae_pct":"","mfe_pct":"","pnl":"","realized_slippage_pct":"","regime":"bull-calm","side":"BUY","sl_pct":"0.015","source":"confluence_signal","timestamp":"2026-05-01T10:35:44+00:00","tp_pct":"0.02","trade_id":"4eaae837289d"},{"_pnl_f":null,"_ts":"2026-05-01T10:35:59+00:00","cloid":"","close_reason":"","coin":"MERL","direction":"BUY","engine":"CONFLUENCE_FUNDING+SNIPER","entry":"","entry_price":"0.032179","event_seq":"2469","event_type":"ENTRY_UPDATE","exchange_fill_id":"","exit_price":"","expected_edge_at_entry":"","funding_paid_pct":"","mae_pct":"","mfe_pct":"","pnl":"","realized_slippage_pct":"-0.0018920595533498312","regime":"","side":"BUY","sl_pct":"","source":"protection_placed","timestamp":"2026-05-01T10:35:59+00:00","tp_pct":"","trade_id":"4eaae837289d"},{"_pnl_f":null,"_ts":"2026-05-01T10:36:21+00:00","cloid":"31db852eSEIL","close_reason":"","coin":"SEI","direction":"BUY","engine":"INV_CONFLUENCE_BTC_WALL+DAY+SNIPER","entry":"0.05766","entry_price":"0.05766","event_seq":"2470","event_type":"ENTRY","exchange_fill_id":"","exit_price":"","expected_edge_at_entry":"0.0136","funding_paid_pct":"","mae_pct":"","mfe_pct":"","pnl":"","realized_slippage_pct":"","regime":"bull-calm","side":"BUY","sl_pct":"0.005","source":"confluence_signal","timestamp":"2026-05-01T10:36:21+00:00","tp_pct":"0.015","trade_id":"31db852e8d4d"},{"_pnl_f":null,"_ts":"2026-05-01T10:36:22+00:00","cloid":"d3598584NEOL","close_reason":"exchange_fill","coin":"NEO","direction":"CLOSE","engine":"INV_CONFLUENCE_BTC_WALL+SNIPER","entry":"","entry_price":"2.713","event_seq":"2471","event_type":"CLOSE","exchange_fill_id":"","exit_price":"","expected_edge_at_entry":"0.0136","funding_paid_pct":"2.503159956799613e-07","mae_pct":"","mfe_pct":"","pnl":"","realized_slippage_pct":"","regime":"bull-calm","side":"BUY","sl_pct":"0.005","source":"reconcile_missing_close","timestamp":"2026-05-01T10:36:22+00:00","tp_pct":"0.015","trade_id":"d3598584c518"},{"_pnl_f":null,"_ts":"2026-05-01T10:36:37+00:00","cloid":"","close_reason":"","coin":"SEI","direction":"BUY","engine":"INV_CONFLUENCE_BTC_WALL+DAY+SNIPER","entry":"","entry_price":"0.057147","event_seq":"2472","event_type":"ENTRY_UPDATE","exchange_fill_id":"","exit_price":"","expected_edge_at_entry":"","funding_paid_pct":"","mae_pct":"","mfe_pct":"","pnl":"","realized_slippage_pct":"-0.008896982310093645","regime":"","side":"BUY","sl_pct":"","source":"protection_placed","timestamp":"2026-05-01T10:36:37+00:00","tp_pct":"","trade_id":"31db852e8d4d"},{"_pnl_f":null,"_ts":"2026-05-01T10:36:37+00:00","cloid":"1b6618fcSNXL","close_reason":"","coin":"SNX","direction":"BUY","engine":"INV_CONFLUENCE_BTC_WALL+SNIPER","entry":"0.3072","entry_price":"0.3072","event_seq":"2473","event_type":"ENTRY","exchange_fill_id":"","exit_price":"","expected_edge_at_entry":"0.0136","funding_paid_pct":"","mae_pct":"","mfe_pct":"","pnl":"","realized_slippage_pct":"","regime":"bull-calm","side":"BUY","sl_pct":"0.005","source":"confluence_signal","timestamp":"2026-05-01T10:36:37+00:00","tp_pct":"0.015","trade_id":"1b6618fcf353"},{"_pnl_f":null,"_ts":"2026-05-01T10:36:52+00:00","cloid":"","close_reason":"","coin":"SNX","direction":"BUY","engine":"INV_CONFLUENCE_BTC_WALL+SNIPER","entry":"","entry_price":"0.31011","event_seq":"2474","event_type":"ENTRY_UPDATE","exchange_fill_id":"","exit_price":"","expected_edge_at_entry":"","funding_paid_pct":"","mae_pct":"","mfe_pct":"","pnl":"","realized_slippage_pct":"0.009472656250000077","regime":"","side":"BUY","sl_pct":"","source":"protection_placed","timestamp":"2026-05-01T10:36:52+00:00","tp_pct":"","trade_id":"1b6618fcf353"},{"_pnl_f":null,"_ts":"2026-05-01T10:36:52+00:00","cloid":"363c750aTAOL","close_reason":"","coin":"TAO","direction":"BUY","engine":"INV_CONFLUENCE_BTC_WALL+DAY","entry":"253.0","entry_price":"253.0","event_seq":"2475","event_type":"ENTRY","exchange_fill_id":"","exit_price":"","expected_edge_at_entry":"0.0136","funding_paid_pct":"","mae_pct":"","mfe_pct":"","pnl":"","realized_slippage_pct":"","regime":"bull-calm","side":"BUY","sl_pct":"0.005","source":"confluence_signal","timestamp":"2026-05-01T10:36:52+00:00","tp_pct":"0.015","trade_id":"363c750aed08"},{"_pnl_f":-0.008896982310093645,"_ts":"2026-05-01T10:36:59+00:00","cloid":"31db852eSEIL","close_reason":"sl","coin":"SEI","direction":"CLOSE","engine":"INV_CONFLUENCE_BTC_WALL+DAY+SNIPER","entry":"0.057147","entry_price":"0.057147","event_seq":"2476","event_type":"CLOSE","exchange_fill_id":"","exit_price":"0.057147","expected_edge_at_entry":"0.0136","funding_paid_pct":"-6.639740782290698e-08","mae_pct":"-0.008896982310093645","mfe_pct":"0.0","pnl":"-0.008896982310093645","realized_slippage_pct":"-0.008896982310093645","regime":"bull-calm","side":"BUY","sl_pct":"0.005","source":"confluence_close","timestamp":"2026-05-01T10:36:59+00:00","tp_pct":"0.015","trade_id":"31db852e8d4d"},{"_pnl_f":1.914,"_ts":"2026-05-01T10:41:34+00:00","cloid":"363c750aTAOL","close_reason":"exchange_fill","coin":"TAO","direction":"CLOSE","engine":"INV_CONFLUENCE_BTC_WALL+DAY","entry":"264.0","entry_price":"253.0","event_seq":"2477","event_type":"CLOSE","exchange_fill_id":"406108168016","exit_price":"264.0","expected_edge_at_entry":"0.0136","funding_paid_pct":"9.791633875833617e-07","mae_pct":"","mfe_pct":"","pnl":"1.914","realized_slippage_pct":"","regime":"bull-calm","side":"BUY","sl_pct":"0.005","source":"reconcile_missing_close","timestamp":"2026-05-01T10:41:34+00:00","tp_pct":"0.015","trade_id":"363c750aed08"},{"_pnl_f":0.7125,"_ts":"2026-05-01T12:29:28+00:00","cloid":"4eaae837MERLL","close_reason":"exchange_fill","coin":"MERL","direction":"CLOSE","engine":"CONFLUENCE_FUNDING+SNIPER","entry":"0.032701","entry_price":"0.032179","event_seq":"2478","event_type":"CLOSE","exchange_fill_id":"406209940637","exit_price":"0.032701","expected_edge_at_entry":"0.018600000000000002","funding_paid_pct":"-0.0001320114","mae_pct":"0.0","mfe_pct":"0.020226185297955595","pnl":"0.7125","realized_slippage_pct":"-0.0018920595533498312","regime":"bull-calm","side":"BUY","sl_pct":"0.015","source":"reconcile_missing_close","timestamp":"2026-05-01T12:29:28+00:00","tp_pct":"0.02","trade_id":"4eaae837289d"}],"losses":10,"no_pnl_recorded":117,"noise_engines":["RECONCILED","untagged_legacy"],"overall_wr_pct":54.5,"real_engines_losses":10,"real_engines_pnl":3.4271,"real_engines_wins":12,"real_engines_wr_pct":54.5,"total_logged":215,"total_pnl":3.4271,"window_hours":12,"wins":12}
,
  "perf_status": {"check_count":212,"enabled":true,"is_warning":false,"last_check_age_sec":39,"last_check_ts":1777644388,"last_warning_ts":0,"loss_ratio_threshold":2.0,"min_closes":10,"recent_transitions":[],"running":true,"system":"b","trigger_count":0,"uptime_sec":12700,"warning_age_sec":null,"warning_duration_s":900,"warning_remaining_s":null,"window_hours":1.0,"window_stats":{"avg_loss_usd":0.0,"avg_win_usd":0.0,"loss_ratio":null,"losses":0,"n":0,"wins":0,"wr_pct":null},"wr_threshold_pct":30.0}
,
  "btcd_status": {"btc_price":78666.0,"btcd_change_pct":-0.1048,"btcd_proxy_now":33.919455,"btcd_proxy_pre":33.955034,"default_config":{"lookback_min":240,"threshold_pct":0.5},"enabled":true,"engine_filter":[],"engine_filter_active":false,"errors":3,"eth_price":2319.2,"fetch_count":39,"interpretation":"alts strong vs BTC \u2014 favor LONGS, block SHORTS","last_err":null,"last_refresh_age_sec":294,"last_refresh_ts":1777644132.922611,"lookback_min_used":60,"refresh_interval_s":300,"regime_at_last_refresh":"bull-calm","regime_configs":{"bear-calm":{"lookback_min":60,"threshold_pct":0.1},"bear-storm":{"lookback_min":30,"threshold_pct":0.5},"bull-calm":{"lookback_min":60,"threshold_pct":0.1},"bull-storm":{"lookback_min":30,"threshold_pct":0.5},"chop":{"lookback_min":360,"threshold_pct":0.5}},"state":"falling","threshold_pct_used":0.1}
,
  "precog_status": {"avg_loss_usd":-0.0058,"avg_win_usd":0.7879,"breakevens_window":51,"by_coin":{"ANIME":{"b":5,"l":0,"n":5,"pnl_usd":0.0,"w":0,"wr_pct":null},"ETC":{"b":0,"l":0,"n":1,"pnl_usd":0.0001,"w":1,"wr_pct":100.0},"IP":{"b":3,"l":0,"n":3,"pnl_usd":0.0,"w":0,"wr_pct":null},"JUP":{"b":3,"l":0,"n":3,"pnl_usd":0.0,"w":0,"wr_pct":null},"LAYER":{"b":3,"l":0,"n":3,"pnl_usd":0.0,"w":0,"wr_pct":null},"LDO":{"b":0,"l":0,"n":1,"pnl_usd":0.0,"w":0,"wr_pct":null},"MOVE":{"b":4,"l":0,"n":4,"pnl_usd":0.0,"w":0,"wr_pct":null},"NEO":{"b":3,"l":0,"n":4,"pnl_usd":0.0,"w":0,"wr_pct":null},"PROVE":{"b":0,"l":1,"n":1,"pnl_usd":-0.0003,"w":0,"wr_pct":0.0},"PUMP":{"b":2,"l":0,"n":2,"pnl_usd":0.0,"w":0,"wr_pct":null},"SEI":{"b":6,"l":2,"n":8,"pnl_usd":-0.0174,"w":0,"wr_pct":0.0},"SNX":{"b":3,"l":0,"n":4,"pnl_usd":0.4496,"w":1,"wr_pct":100.0},"SOL":{"b":2,"l":0,"n":2,"pnl_usd":0.0,"w":0,"wr_pct":null},"STABLE":{"b":2,"l":0,"n":2,"pnl_usd":0.0,"w":0,"wr_pct":null},"SUSHI":{"b":2,"l":0,"n":2,"pnl_usd":0.0,"w":0,"wr_pct":null},"TAO":{"b":4,"l":0,"n":5,"pnl_usd":1.914,"w":1,"wr_pct":100.0},"TURBO":{"b":0,"l":1,"n":1,"pnl_usd":-0.0053,"w":0,"wr_pct":0.0},"UMA":{"b":1,"l":0,"n":1,"pnl_usd":0.0,"w":0,"wr_pct":null},"W":{"b":4,"l":0,"n":4,"pnl_usd":0.0,"w":0,"wr_pct":null},"XRP":{"b":4,"l":0,"n":4,"pnl_usd":0.0,"w":0,"wr_pct":null}},"by_engine":{"INV_CONFLUENCE_BTC_WALL+DAY":{"b":16,"l":0,"n":17,"pnl_usd":1.914,"w":1,"wr_pct":100.0},"INV_CONFLUENCE_BTC_WALL+DAY+SNIPER":{"b":15,"l":3,"n":19,"pnl_usd":-0.0227,"w":0,"wr_pct":0.0},"INV_CONFLUENCE_BTC_WALL+SNIPER":{"b":14,"l":1,"n":17,"pnl_usd":0.4493,"w":1,"wr_pct":50.0},"INV_CONFLUENCE_NEWS+SNIPER":{"b":6,"l":0,"n":7,"pnl_usd":0.0001,"w":1,"wr_pct":100.0}},"closed_count":60,"disabled_engines":null,"enabled":true,"engine_auto_pause":{},"losses_window":4,"risk_pct":0.01,"system":"A","total_pnl_usd":2.3406,"window_hours":12.0,"wins_window":3,"wr_pct_window":42.9}
,
  "confluence_trades": {"_err": "http_000curl_err"}
,
  "confluence_status": {"_err": "http_000curl_err"}
,
  "postmortem_status": {"dry_run":false,"enabled":true,"has_api_key":false,"ok":true,"recent_runs":[{"agents_run":4,"coin":"kNEIRO","deltas_applied":2,"duration_s":45319.717123031616,"engine":"PIVOT","entry_px":0.08969,"exit_reason":"sl_hit","id":3,"is_win":0,"pnl_pct":-2.1756108445832796,"pos_json":"{\"side\": \"S\", \"opened_at\": 1776929710.107852, \"entry\": 0.08969, \"stage\": \"initial\", \"peak\": 0.08969, \"engine\": \"PIVOT\", \"conf\": 30, \"utc_h\": 7, \"sl_pct\": null, \"tp_pct\": null, \"sigs\": [\"PV\"], \"size\": 1370.0, \"exit_reason\": \"sl_hit\"}","side":"S","status":"complete:kNEIRO short entered at conf=30 during chop regime with negative funding, aligned with macro bearish backdrop. Trade was stopped out at -2.176% after 12.6 hours due to volatility whipsaw typical of choppy conditions. Operational execution was clean; loss was directional, not structural. Single sample with no prior pattern data.","synthesis_json":"{\"root_cause\": \"kNEIRO short entered at conf=30 during chop regime with negative funding, aligned with macro bearish backdrop. Trade was stopped out at -2.176% after 12.6 hours due to volatility whipsaw typical of choppy conditions. Operational execution was clean; loss was directional, not structural. Single sample with no prior pattern data.\", \"decisions\": [{\"component\": \"entry_confidence_filter\", \"param\": \"min_conf_chop_regime\", \"decision\": \"DEFER\", \"note\": \"Proposed increase from 30\\u219245 for chop regime entries is directionally sound but premature. Need 3+ samples showing conf<45 failures in chop before raising threshold. Current loss (-2.176%) is within acceptable range for regime volatility.\"}], \"new_vetos\": [], \"kb_entries\": [{\"pattern_key\": \"kNEIRO:S:regime=chop\", \"summary\": \"First kNEIRO short in chop regime: conf=30, negative funding aligned, SL hit -2.176% after 12.6h. Regime whipsaw likely cause. Need more samples to establish pattern.\", \"evidence\": {\"pnl\": \"-2.176%\", \"conf\": 30, \"duration_h\": 12.6, \"regime\": \"chop\", \"funding_btc_bps\": -0.67, \"funding_eth_bps\": -0.57, \"exit_reason\": \"sl_hit\", \"log_id\": 3, \"root_cause\": \"kNEIRO short entered at conf=30 during chop regime with negative funding, aligned with macro bearish backdrop. Trade was stopped out at -2.176% after 12.6 hours due to volatility whipsaw typical of choppy conditions. Operational execution was clean; loss was directional, not structural. Single sampl\"}}, {\"pattern_key\": \"kNEIRO:S\", \"summary\": \"Baseline kNEIRO short: PIVOT engine, Asian session entry (07:00 UTC), chop regime, -2.176% loss via SL. Macro bearish (neg funding/mcap) but chop volatility dominated.\", \"evidence\": {\"engine\": \"PIVOT\", \"session\": \"asian\", \"entry_utc_h\": 7, \"pnl\": \"-2.176%\", \"sample_count\": 1, \"log_id\": 3, \"root_cause\": \"kNEIRO short entered at conf=30 during chop regime with negative funding, aligned with macro bearish backdrop. Trade was stopped out at -2.176% after 12.6 hours due to volatility whipsaw typical of choppy conditions. Operational execution was clean; loss was directional, not structural. Single sampl\"}}]}","ts":1776975029.865129},{"agents_run":4,"coin":"BABY","deltas_applied":2,"duration_s":35627.43404006958,"engine":"PIVOT","entry_px":0.015796,"exit_reason":"sl_hit","id":2,"is_win":0,"pnl_pct":-2.051671732522783,"pos_json":"{\"side\": \"S\", \"opened_at\": 1776935267.4964552, \"entry\": 0.015796, \"stage\": \"initial\", \"peak\": 0.015796, \"engine\": \"PIVOT\", \"conf\": 40, \"utc_h\": 9, \"sl_pct\": 0.03, \"tp_pct\": 0.08, \"sigs\": [\"PV\", \"BB\"], \"size\": 5453.0, \"exit_reason\": \"sl_hit\"}","side":"S","status":"complete:BABY short on PIVOT engine entered during choppy regime with low confidence (40) and negative funding. Trade hit 3% stop-loss at -2.052% after 9.9 hours. All agents confirm proper execution and regime alignment (chop + negative funding favors shorts), but choppy conditions naturally punish directional pivots. Loss reflects expected variance on a low-confidence signal in non-trending market, not a systemic flaw.","synthesis_json":"{\"root_cause\": \"BABY short on PIVOT engine entered during choppy regime with low confidence (40) and negative funding. Trade hit 3% stop-loss at -2.052% after 9.9 hours. All agents confirm proper execution and regime alignment (chop + negative funding favors shorts), but choppy conditions naturally punish directional pivots. Loss reflects expected variance on a low-confidence signal in non-trending market, not a systemic flaw.\", \"decisions\": [], \"new_vetos\": [], \"kb_entries\": [{\"pattern_key\": \"BABY:S:engine=PIVOT\", \"summary\": \"PIVOT short on BABY in chop regime (conf=40) hit SL at -2.052%. Choppy conditions favor mean-reversion over directional pivots. Single sample; monitor for pattern.\", \"evidence\": {\"regime\": \"chop\", \"confidence\": 40, \"exit_reason\": \"sl_hit\", \"pnl_pct\": -2.051671732522783, \"funding_bps\": -0.791, \"log_id\": 2, \"root_cause\": \"BABY short on PIVOT engine entered during choppy regime with low confidence (40) and negative funding. Trade hit 3% stop-loss at -2.052% after 9.9 hours. All agents confirm proper execution and regime alignment (chop + negative funding favors shorts), but choppy conditions naturally punish direction\"}}, {\"pattern_key\": \"BABY:S:regime=chop\", \"summary\": \"BABY short in chop regime with negative funding hit 3% SL. Regime-aligned but non-trending conditions limit directional edge. Acceptable variance on low-conf signal.\", \"evidence\": {\"engine\": \"PIVOT\", \"confidence\": 40, \"session\": \"asian\", \"pnl_pct\": -2.051671732522783, \"log_id\": 2, \"root_cause\": \"BABY short on PIVOT engine entered during choppy regime with low confidence (40) and negative funding. Trade hit 3% stop-loss at -2.052% after 9.9 hours. All agents confirm proper execution and regime alignment (chop + negative funding favors shorts), but choppy conditions naturally punish direction\"}}]}","ts":1776970894.9739075},{"agents_run":4,"coin":"ARB","deltas_applied":2,"duration_s":31892.783497333527,"engine":"RECONCILED","entry_px":0.12654,"exit_reason":"sl_hit","id":1,"is_win":0,"pnl_pct":-2.094199462620504,"pos_json":"{\"side\": \"S\", \"opened_at\": 1776929671.6386673, \"entry\": 0.12654, \"stage\": \"initial\", \"peak\": 0.12654, \"engine\": \"RECONCILED\", \"source\": \"reconcile\", \"exit_reason\": \"sl_hit\"}","side":"S","status":"complete:ARB short entered during chop regime with negative cross-venue funding (-0.426% BTC, -0.764% ETH), creating regime mismatch. Chop favors range-bound mean reversion while negative funding signals bearish bias\u2014contradictory forces led to whipsaw and -2.094% stop-loss after 8.9h. Execution was clean; regime incompatibility drove the loss.","synthesis_json":"{\"root_cause\": \"ARB short entered during chop regime with negative cross-venue funding (-0.426% BTC, -0.764% ETH), creating regime mismatch. Chop favors range-bound mean reversion while negative funding signals bearish bias\\u2014contradictory forces led to whipsaw and -2.094% stop-loss after 8.9h. Execution was clean; regime incompatibility drove the loss.\", \"decisions\": [{\"component\": \"funding.neg_threshold_bps\", \"param\": \"neg_threshold_bps\", \"decision\": \"DEFER\", \"note\": \"Single ARB short insufficient to justify tightening neg_threshold from current unknown baseline to -2.0 bps. Need 3+ samples showing chop+neg_funding pattern before changing global funding filter.\"}, {\"component\": \"regime_filter\", \"param\": \"chop_short_veto\", \"decision\": \"APPROVE\", \"note\": \"Regime agent correctly identified chop+negative_funding as whipsaw-prone for shorts. 12h veto is proportionate for monitoring pattern emergence without permanent block.\"}], \"new_vetos\": [{\"component\": \"regime_filter\", \"expires_in_sec\": 43200, \"reason\": \"Suppress short entries during chop regime when cross-venue funding is negative (< -0.5 bps). Chop + negative funding creates whipsaw risk incompatible with directional shorts.\"}], \"kb_entries\": [{\"pattern_key\": \"ARB:S:regime=chop\", \"summary\": \"ARB short in chop regime with negative funding (-0.426% BTC, -0.764% ETH) hit stop-loss at -2.094% after 8.9h. Chop favors range reversals; avoid shorts unless funding >0 or regime shifts.\", \"evidence\": {\"sample_count\": 1, \"loss_rate\": \"1/1\", \"avg_loss_pct\": -2.094, \"regime\": \"chop\", \"funding_btc_pct\": -0.426, \"funding_eth_pct\": -0.764, \"duration_h\": 8.9, \"log_id\": 1, \"root_cause\": \"ARB short entered during chop regime with negative cross-venue funding (-0.426% BTC, -0.764% ETH), creating regime mismatch. Chop favors range-bound mean reversion while negative funding signals bearish bias\\u2014contradictory forces led to whipsaw and -2.094% stop-loss after 8.9h. Execution was clean; r\"}}, {\"pattern_key\": \"ARB:S:funding=neg\", \"summary\": \"First ARB short loss during negative cross-venue funding. Stop-hit at -2.094%. Monitor for pattern; negative funding + chop creates directional conflict for shorts.\", \"evidence\": {\"sample_count\": 1, \"entry_px\": 0.12654, \"exit_reason\": \"sl_hit\", \"funding_context\": \"negative\", \"regime\": \"chop\", \"log_id\": 1, \"root_cause\": \"ARB short entered during chop regime with negative cross-venue funding (-0.426% BTC, -0.764% ETH), creating regime mismatch. Chop favors range-bound mean reversion while negative funding signals bearish bias\\u2014contradictory forces led to whipsaw and -2.094% stop-loss after 8.9h. Execution was clean; r\"}}]}","ts":1776961564.4289315}],"total_components":19}
,
  "postmortem_vetos": {"vetos":[]}
,
  "postmortem_params": {"params":[]}
,
  "regime_status": {"config_coverage":{"bear-calm":"7/57 (12%)","bear-storm":"0/57 (0%)","bull-calm":"41/57 (71%)","bull-storm":"0/57 (0%)","chop":"18/57 (31%)"},"detector":{"btc_dist_from_ema20_1h_pct":1.82,"btc_vol_1h_pct":0.304,"current_regime":"bull-calm","ema_period":20,"hysteresis_bars_1h":2,"last_check_age_sec":3,"raw_1h":"bull-calm","raw_30m":"bull-calm","recent_history_1h":["bull-calm","bull-calm"],"trend_buffer_pct":0.5,"vol_median_split":0.00957},"total_coins_with_regime_configs":57}
}
